2-Lab/mem.sv
module mem #(
    parameter MEM_ADDR_SIZE = 10 + 9, 
    parameter BUS_SIZE = 16 ,
    parameter CACHE_OFFSET_SIZE = 4,
    parameter CACHE_LINE_SIZE = 16
    ) (
    input clk,
    input reset,
    input [MEM_ADDR_SIZE-CACHE_OFFSET_SIZE-1:0] address,
    inout [BUS_SIZE-1:0] data,
    input [2-1:0] command
);

    // 512KB = 2^9 * 2^10 = 2^19 = 2^15 lines * 2^4 bits in each line (16 8-bit words)
    parameter MEM_SIZE = 1 << (MEM_ADDR_SIZE-CACHE_OFFSET_SIZE); // 2^15 cache lines

    localparam  C2_NOP      = 3'd0,
                C2_RESPONSE = 3'd1,
                C2_READ     = 3'd2,
                C2_WRITE    = 3'd3;

    reg [CACHE_LINE_SIZE*8-1:0] storage [MEM_SIZE-1:0]; // 2^15 16-byte lines
    reg [BUS_SIZE-1:0] data_buff; // single bus
    reg [2-1:0] command_buff;

    reg [CACHE_OFFSET_SIZE-1:0] rwPosition; // ptr to next 2 bytes to read/write

    integer SEED = 225526;



    always @(posedge clk or posedge reset) begin
        if (reset) begin
            for (int i = 0; i < 99; i=i+1) begin
                storage[i] = $random(SEED)>>16;
            end
            $display("filled");

            data_buff = 'z;
            command_buff = 0;
            rwPosition = 0;
        end else begin
            command_buff = 0;
            if (command == C2_READ) begin
                // READ
                for (int i=0; i<CACHE_LINE_SIZE; i=i+1) begin
                    data_buff[i] = storage[address][rwPosition*8 + i];
                end
                rwPosition += 2;
            end else if (command == C2_WRITE) begin
                // WRITE
                // $display("before: %b", storage[address]);
                for (int i=0; i<CACHE_LINE_SIZE; i=i+1) begin
                    storage[address][rwPosition*8 + i] = data[i];
                end
                // $display("after : %b", storage[address]);
                rwPosition += 2;
            end else begin
                rwPosition = 0;
                data_buff = 'z;
            end
        end
    end

    assign data = data_buff;

endmodule

2-Lab/cache.sv
module cache#(
    parameter BUS_SIZE = 16 ,
    parameter MEM_ADDR_SIZE = 10 + 9,   // log2(MEM_SIZE)
    parameter CACHE_OFFSET_SIZE = 4,    // log2(CACHE_LINE_SIZE)
    parameter CACHE_LINE_SIZE   = 16
    ) (
    input clk,
    input reset,
    input [MEM_ADDR_SIZE-CACHE_OFFSET_SIZE-1:0] cpu_address,
    inout [BUS_SIZE-1:0] cpu_data,
    inout [3-1:0] cpu_command,

    output [MEM_ADDR_SIZE-CACHE_OFFSET_SIZE-1:0] mem_address,
    inout [BUS_SIZE-1:0] mem_data,
    inout [2-1:0] mem_command
);

    parameter CACHE_WAY         = 2;

    parameter CACHE_LINE_COUNT  = 64;
    parameter CACHE_SETS_COUNT  = CACHE_LINE_COUNT/CACHE_WAY; 
    parameter CACHE_SIZE        = CACHE_LINE_COUNT * CACHE_LINE_SIZE;
   
    parameter CACHE_SET_SIZE    = 5;    // log2(CACHE_SETS_COUNT)
    parameter CACHE_TAG_SIZE    = 10;   // CACHE_LINE_SIZE - CACHE_SET_SIZE - CACHE_OFFSET_SIZE
    localparam  C1_NOP          = 3'd0,
                C1_READ8        = 3'd1,
                C1_READ16       = 3'd2,
                C1_READ32       = 3'd3,
                C1_INV_LINE     = 3'd4,
                C1_WRITE8       = 3'd5,
                C1_WRITE16      = 3'd6,
                C1_WRITE32_RESP = 3'd7;

    localparam  C2_NOP          = 2'd0,
                C2_RESPONSE     = 2'd1,
                C2_READ         = 2'd2,
                C2_WRITE        = 2'd3;

    // localparam  IDLE        = 3'd0,
    //             READ        = 3'd1,
    //             WRITE       = 3'd2,
    //             READMM      = 3'd3,
    //             WAITFORMM   = 3'd4,
    //             UPDATEMM    = 3'd5,
    //             UPDATECACHE = 3'd6;

    // reg [3-1:0] state;

    // STORAGE
    reg valid_array [CACHE_SETS_COUNT-1:0][CACHE_WAY-1:0];
    reg dirty_array [CACHE_SETS_COUNT-1:0][CACHE_WAY-1:0];
    reg last_used_array [CACHE_SETS_COUNT-1:0]; // lRU
    reg [CACHE_TAG_SIZE-1:0] tag_array [CACHE_SETS_COUNT-1:0][CACHE_WAY-1:0];
    reg [CACHE_LINE_SIZE*8-1:0] data_array [CACHE_SETS_COUNT-1:0][CACHE_WAY-1:0]; // stores lines

    reg [MEM_ADDR_SIZE-1:0] cpu_address_buff;
    reg [CACHE_TAG_SIZE-1:0] cpu_tag_buff;
    reg [CACHE_SET_SIZE-1:0] cpu_set_buff;
    reg [CACHE_OFFSET_SIZE-1:0] cpu_offset_buff;
    reg [BUS_SIZE-1:0] cpu_data_bus_buff; // single bus
    reg [3-1:0] cpu_command_buff;
    
    reg [MEM_ADDR_SIZE-CACHE_OFFSET_SIZE-1:0] mem_address_buff;
    reg [CACHE_LINE_SIZE*8-1:0] mem_line_buff; // single line
    // reg [BUS_SIZE-1:0] mem_data_buff;
    reg [2-1:0] mem_command_buff;
    

    task delay;
        begin
            @(negedge clk);
        end
    endtask	

    initial begin
        mem_line_buff = 0;
        cpu_data_bus_buff = 0;
        cpu_command_buff = 'z;
    end

    always @(posedge clk or posedge reset) begin
        if (reset) begin
            for (int i=0; i<CACHE_SETS_COUNT; i=i+1) begin
                valid_array[i][0] = 0;
                dirty_array[i][0] = 0;
                tag_array[i][0]   = 'z;
                data_array[i][0]  = 'z;
                valid_array[i][1] = 0;
                dirty_array[i][1] = 0;
                tag_array[i][1]   = 'z;
                data_array[i][1]  = 'z;
            end
        end 
        if (cpu_command == C1_READ8) begin
            $display("C1_READ8");

            mem_address_buff = cpu_address;
            cpu_tag_buff = cpu_address[CACHE_TAG_SIZE+CACHE_SET_SIZE-1:CACHE_SET_SIZE];
            cpu_set_buff = cpu_address[CACHE_SET_SIZE-1:0];
            while (mem_address_buff == cpu_address) begin 
                delay;
            end
            cpu_offset_buff = cpu_address[3:0];
            if (tag_array[cpu_set_buff][0] == cpu_tag_buff) begin
                $display("found0");
                if (valid_array[cpu_set_buff][0] == 1) begin
                    cpu_data_bus_buff = data_array[cpu_set_buff][0][cpu_offset_buff*8 +: 8];
                end
            end else if (tag_array[cpu_set_buff][1] == cpu_tag_buff) begin
                $display("found1");
                if (valid_array[cpu_set_buff][1] == 1) begin
                    cpu_data_bus_buff = data_array[cpu_set_buff][1][cpu_offset_buff*8 +: 8];
                end
            end else begin // GO TO MM
                $display("GO TO MM");
                // set
                mem_command_buff = C2_READ;
                delay;
                // read
                for (int i=0; i<CACHE_LINE_SIZE/2; i=i+1) begin
                    mem_line_buff[BUS_SIZE*i +: BUS_SIZE] = mem_data;
                    delay;
                end
                mem_command_buff = C2_NOP;
                // write in cache storage
                if (valid_array[cpu_set_buff][0] == 0) begin
                    $display("store to 0");
                    data_array[cpu_set_buff][0] = mem_line_buff;
                    tag_array[cpu_set_buff][0] = cpu_tag_buff;
                    valid_array[cpu_set_buff][0] = 1;
                    dirty_array[cpu_set_buff][0] = 0;
                    last_used_array[cpu_set_buff] = 1; // opposite 
                end else if (valid_array[cpu_set_buff][1] == 0) begin
                    $display("store to 1");
                    data_array[cpu_set_buff][1] = mem_line_buff;
                    tag_array[cpu_set_buff][1] = cpu_tag_buff;
                    valid_array[cpu_set_buff][1] = 1;
                    dirty_array[cpu_set_buff][1] = 0;
                    last_used_array[cpu_set_buff] = 0; // opposite 
                end else begin
                    if (dirty_array[cpu_set_buff][last_used_array[cpu_set_buff]] == 1) begin
                    $display("write to mm");
                        // write to MM
                    end
                end
                cpu_data_bus_buff = mem_line_buff[cpu_offset_buff*8 +: 8];
            end

            cpu_command_buff = C1_WRITE32_RESP;
            delay;
            cpu_command_buff = 'z;

        end else if (cpu_command == C1_WRITE8) begin
            
        end
    end
    assign mem_command = mem_command_buff;
    assign mem_address = mem_address_buff;
    assign cpu_data = cpu_data_bus_buff;
    assign cpu_command = cpu_command_buff;

    // always @(posedge clk) begin
    //     case(state)
    //         IDLE: begin
    //             case (cpu_command)
    //                 C1_NOP: begin
                        
    //                 end
    //                 C1_READ8: begin
    //                     state = READ;
    //                     mem_address_buff = cpu_address;
    //                     bitOfOp = 8;
    //                 end
    //                 C1_READ16: begin
                        
    //                     bitOfOp = 16;
    //                 end
    //                 C1_READ32: begin
                        
    //                     bitOfOp = 32;
    //                 end
    //                 C1_INV_LINE: begin
                        
    //                 end
    //                 C1_WRITE8: begin
                        
    //                     bitOfOp = 8;
    //                 end
    //                 C1_WRITE16: begin
                        
    //                     bitOfOp = 16;
    //                 end
    //                 C1_WRITE32: begin
                        
    //                     bitOfOp = 32;
    //                 end
    //             endcase
    //         end
    //         READ: begin
    //             reg [CACHE_SET_SIZE-1:0] set = cpu_address >> CACHE_OFFSET_SIZE;
    //             reg [CACHE_TAG_SIZE-1:0] tag = cpu_address >> (CACHE_SET_SIZE + CACHE_OFFSET_SIZE);

    //             if (valid_array[set][0] == 1 && tag_array[set][0] == tag) begin

    //             end else if (valid_array[set][1] == 1 && tag_array[set][1] == tag) begin
                    
    //             end else begin
    //                 // miss
    //                 if (dirty_array[set][last_used_array[set]] == 1) begin
    //                     // UPDATEMM
    //                     // dirty
    //                     // flag
    //                 end else begin
    //                     // READMM
    //                 end
    //             end

    //             assign hit_w0 = vw0 & (tagdata == rtag0[10:0]);
    //             assign hit_w1 = vw1 & (tagdata == rtag1[10:0]);
    //             assign hit = hit_w0 | hit_w1;
    //         end
    //         WRITE: begin
                
    //         end
    //         READMM: begin
                
    //         end
    //         WAITFORMM: begin
                
    //         end
    //         UPDATEMM: begin
                
    //         end
    //         UPDATECACHE: begin
                
    //         end
    //     endcase
    // end

    // assign mem_address = mem_address_buff;

    // // CPU
    // always @(posedge clk) begin
    //     mem_command_buff = 0;
    //     // C1_READ8
    //     if (cpu_command == 3) begin
    //         reg [CACHE_SET_SIZE-1:0] set = cpu_address >> CACHE_OFFSET_SIZE;
    //         reg [CACHE_TAG_SIZE-1:0] tag = cpu_address >> (CACHE_SET_SIZE + CACHE_OFFSET_SIZE);
    //         reg found = 0;
    //         for (int i=0; i<CACHE_SET_SIZE; i=i+1) begin
    //             if (tag_array[set][i] == tag) begin
    //                 // Retrurn data
    //                 cpu_data_buff = data_array[set][i];
    //                 cpu_command_buff = 7;
    //             end
    //         end

    //         if (found == 0) begin 
    //             // Request from mem
    //             // Set valid 
    //             valid_array[set][i] = 1;
    //         end

    //     end
    // end
    // assign mem_command = mem_command_buff;
    // assign mem_data = mem_line_buff;

    // // MEM
    // always @(posedge clk) begin
    //     cpu_command_buff = 0;
    //     // C2_READ
    //     if (mem_command == 1) begin
    //         reg [CACHE_SET_SIZE-1:0] set = mem_address >> CACHE_OFFSET_SIZE;
    //         reg [CACHE_TAG_SIZE-1:0] tag = mem_address >> (CACHE_SET_SIZE + CACHE_OFFSET_SIZE);
    //         reg found = 0;
    //         for (int i=0; i<CACHE_SET_SIZE; i=i+1) begin
    //             if (valid_array[set][i] == 0) begin
    //                 found = 1;
    //                 valid_array[set][i] = 1;
    //                 dirty_array[set][i] = 0;
    //                 tag_array[set][i] = tag;
    //                 data_array[set][i] = mem_data;
    //             end
    //         end
    //         if (found == 0) begin
    //             // search for not dirty
    //             // if all dirty write one and replace with new data
    //         end
    //         cpu_data_buff = mem_data;

    //         cpu_command_buff = 7;
    //     end
    // end
    // assign cpu_command = cpu_command_buff;
    // assign cpu_data = cpu_data_buff;

    

endmodule

2-Lab/cpu.sv
module cpu #(
    parameter MEM_ADDR_SIZE = 10 + 9, 
    parameter BUS_SIZE = 16,
    parameter CACHE_OFFSET_SIZE = 4
    ) (

    input clk,
    output [MEM_ADDR_SIZE-CACHE_OFFSET_SIZE-1:0] address,
    inout [BUS_SIZE-1:0] data,
    inout [3-1:0] command
);

    localparam  C1_NOP          = 3'd0,
                C1_READ8        = 3'd1,
                C1_READ16       = 3'd2,
                C1_READ32       = 3'd3,
                C1_INV_LINE     = 3'd4,
                C1_WRITE8       = 3'd5,
                C1_WRITE16      = 3'd6,
                C1_WRITE32_RESP = 3'd7;
    
    reg [3-1:0] cpu_command_buff;
    reg [MEM_ADDR_SIZE-1:0] cpu_address_buff;
    reg [BUS_SIZE-1:0] recieved_data;

    task delay;
        begin
            @(negedge clk);
        end
    endtask	
    
    // Place for test calls
    initial begin
        recieved_data = 0;
        delay;
        // READ
        cpu_command_buff = C1_READ8;
        cpu_address_buff = 15'b000000000000011;
        delay;
        cpu_address_buff = 15'b0000;
        delay;
        cpu_command_buff = 'z;
        delay;
        while (command !== C1_WRITE32_RESP) begin 
            delay;
        end
        recieved_data = data;
        $display("recieved: %b", recieved_data);
        // READ2
        cpu_command_buff = C1_READ8;
        cpu_address_buff = 15'b000000000000011;
        delay;
        cpu_address_buff = 15'b0001;
        delay;
        cpu_command_buff = 'z;
        delay;
        while (command !== C1_WRITE32_RESP) begin 
            delay;
        end
        recieved_data = data;
        $display("recieved: %b", recieved_data);
        $finish();
    end
    assign command = cpu_command_buff;
    assign address = cpu_address_buff;
endmodule

2-Lab/testbench.sv
module testbench ();
    parameter BUS_SIZE = 16;
    parameter MEM_ADDR_SIZE = 10 + 9;   // log2(MEM_SIZE)
    parameter CACHE_OFFSET_SIZE = $clog2(CACHE_LINE_SIZE);
    parameter CACHE_LINE_SIZE = 16;
    wire [MEM_ADDR_SIZE-CACHE_OFFSET_SIZE-1:0] cpu_address;
    wire [BUS_SIZE-1:0] cpu_data;
    wire [3-1:0] cpu_command;
    wire [MEM_ADDR_SIZE-CACHE_OFFSET_SIZE-1:0] mem_address;
    wire [BUS_SIZE-1:0] mem_data;
    wire [2-1:0] mem_command;

    reg clk;
    reg reset;


    cpu #(MEM_ADDR_SIZE, BUS_SIZE, CACHE_OFFSET_SIZE) 
    cpu (clk, cpu_address, cpu_data, cpu_command);

    cache #(BUS_SIZE, MEM_ADDR_SIZE, CACHE_OFFSET_SIZE, CACHE_LINE_SIZE)
    cache (clk, reset, 
    cpu_address, cpu_data, cpu_command,
    mem_address, mem_data, mem_command);

    mem #(MEM_ADDR_SIZE, BUS_SIZE, CACHE_OFFSET_SIZE, CACHE_LINE_SIZE) 
    mem(clk, reset, mem_address, mem_data, mem_command);

     task delay;
        begin
            @(negedge clk);
        end
    endtask	

    initial begin
        reset = 0;
        #1 reset = 1;
        #1 reset = 0;
        clk = 1'd0;

        forever begin
            #1 clk = ~clk;
            // $display("addr: %b", mem_address);
            // $display("data: %b", mem_data);
            // $display("cache.: %b", cache.mem_data_buff);
            // $display("mem.: %b", mem.data_buff);
            // $display("command: %b", mem_command);
        end
    end

    initial begin
        $dumpfile("dump_cache.vcd"); 
        $dumpvars;
    end

endmodule

2-Lab/dump_cache.vcd
$date
	Wed Nov 30 01:30:51 2022
$end
$version
	Icarus Verilog
$end
$timescale
	1s
$end
$scope module testbench $end
$var wire 3 ! cpu_command [2:0] $end
$var wire 16 " mem_data [15:0] $end
$var wire 2 # mem_command [1:0] $end
$var wire 15 $ mem_address [14:0] $end
$var wire 16 % cpu_data [15:0] $end
$var wire 15 & cpu_address [14:0] $end
$var reg 1 ' clk $end
$var reg 1 ( reset $end
$scope module cache $end
$var wire 1 ' clk $end
$var wire 3 ) cpu_command [2:0] $end
$var wire 16 * cpu_data [15:0] $end
$var wire 15 + mem_address [14:0] $end
$var wire 2 , mem_command [1:0] $end
$var wire 1 ( reset $end
$var wire 16 - mem_data [15:0] $end
$var wire 15 . cpu_address [14:0] $end
$var reg 3 / cpu_command_buff [2:0] $end
$var reg 16 0 cpu_data_bus_buff [15:0] $end
$var reg 4 1 cpu_offset_buff [3:0] $end
$var reg 5 2 cpu_set_buff [4:0] $end
$var reg 10 3 cpu_tag_buff [9:0] $end
$var reg 15 4 mem_address_buff [14:0] $end
$var reg 2 5 mem_command_buff [1:0] $end
$var reg 128 6 mem_line_buff [127:0] $end
$scope begin $ivl_for_loop0 $end
$var integer 32 7 i [31:0] $end
$upscope $end
$scope begin $ivl_for_loop1 $end
$var integer 32 8 i [31:0] $end
$upscope $end
$scope task delay $end
$upscope $end
$upscope $end
$scope module cpu $end
$var wire 1 ' clk $end
$var wire 3 9 command [2:0] $end
$var wire 16 : data [15:0] $end
$var wire 15 ; address [14:0] $end
$var reg 19 < cpu_address_buff [18:0] $end
$var reg 3 = cpu_command_buff [2:0] $end
$var reg 16 > recieved_data [15:0] $end
$scope task delay $end
$upscope $end
$upscope $end
$scope module mem $end
$var wire 15 ? address [14:0] $end
$var wire 1 ' clk $end
$var wire 2 @ command [1:0] $end
$var wire 16 A data [15:0] $end
$var wire 1 ( reset $end
$var reg 2 B command_buff [1:0] $end
$var reg 16 C data_buff [15:0] $end
$var reg 4 D rwPosition [3:0] $end
$var integer 32 E SEED [31:0] $end
$scope begin $ivl_for_loop2 $end
$var integer 32 F i [31:0] $end
$upscope $end
$scope begin $ivl_for_loop3 $end
$var integer 32 G i [31:0] $end
$upscope $end
$scope begin $ivl_for_loop4 $end
$var integer 32 H i [31:0] $end
$upscope $end
$upscope $end
$upscope $end
$enddefinitions $end
#0
$dumpvars
b0 H
b0 G
b0 F
b110111000011110110 E
bx D
bx C
bx B
bx A
bx @
bx ?
b0 >
bx =
bx <
bx ;
b0 :
bx 9
b0 8
b0 7
b0 6
bx 5
bx 4
bx 3
bx 2
bx 1
b0 0
bz /
bx .
bx -
bx ,
bx +
b0 *
bx )
0(
x'
bx &
b0 %
bx $
bx #
bx "
bx !
$end
#1
b0 D
b0 B
b0 "
b0 -
b0 A
b0 C
b1000 F
b10111101101100001001111000001110 E
b100000 7
1(
#2
b11 &
b11 .
b11 ;
b11 <
b1 !
b1 )
b1 9
b1 =
0'
0(
#3
b11 2
b0 3
b11 $
b11 +
b11 ?
b11 4
1'
#4
b0 &
b0 .
b0 ;
b0 <
0'
#5
1'
#6
b10 #
b10 ,
b10 @
b10 5
b0 1
bz !
bz )
bz 9
bz =
0'
#7
b10 D
b1001010110111100 "
b1001010110111100 -
b1001010110111100 A
b1001010110111100 C
b10000 G
1'
#8
b1001010110111100 6
0'
#9
b100 D
b1111111111111111 "
b1111111111111111 -
b1111111111111111 A
b1111111111111111 C
b10000 G
1'
#10
b11111111111111111001010110111100 6
b1 8
0'
#11
b110 D
b10000 G
1'
#12
b111111111111111111111111111111111001010110111100 6
b10 8
0'
#13
b1000 D
b10000 G
1'
#14
b1111111111111111111111111111111111111111111111111001010110111100 6
b11 8
0'
#15
b1010 D
b10000 G
1'
#16
b11111111111111111111111111111111111111111111111111111111111111111001010110111100 6
b100 8
0'
#17
b1100 D
b10000 G
1'
#18
b111111111111111111111111111111111111111111111111111111111111111111111111111111111001010110111100 6
b101 8
0'
#19
b1110 D
b10000 G
1'
#20
b1111111111111111111111111111111111111111111111111111111111111111111111111111111111111111111111111001010110111100 6
b110 8
0'
#21
b0 D
b0 "
b0 -
b0 A
b0 C
b10000 G
1'
#22
b111 8
0'
#23
b10 D
b1001010110111100 "
b1001010110111100 -
b1001010110111100 A
b1001010110111100 C
b10000 G
1'
#24
b111 !
b111 )
b111 9
b111 /
b10111100 %
b10111100 *
b10111100 :
b10111100 0
b0 #
b0 ,
b0 @
b0 5
b1000 8
0'
#25
b0 D
1'
#26
b11 &
b11 .
b11 ;
bz /
b11 <
b1 !
b1 )
b1 9
b1 =
b10111100 >
0'
#27
1'
#28
b1 &
b1 .
b1 ;
b1 <
0'
#29
1'
#30
b111 /
b10010101 %
b10010101 *
b10010101 :
b10010101 0
b1 1
b111 !
b111 )
b111 9
bz =
0'
#31
1'
#32
bz !
bz )
bz 9
bz /
b10010101 >
0'
