2-Lab/mem.sv
module mem #(
    parameter MEM_ADDR_SIZE = 10 + 9, 
    parameter BUS_SIZE = 16 ,
    parameter CACHE_OFFSET_SIZE = 4,
    parameter CACHE_LINE_SIZE = 16
    ) (
    input clk,
    input reset,
    input [MEM_ADDR_SIZE-CACHE_OFFSET_SIZE-1:0] address,
    inout [BUS_SIZE-1:0] data,
    input [2-1:0] command
);

    // 512KB = 2^9 * 2^10 = 2^19 = 2^15 lines * 2^4 bits in each line (16 8-bit words)
    parameter MEM_SIZE = 1 << (MEM_ADDR_SIZE-CACHE_OFFSET_SIZE); // 2^15 cache lines

    localparam  C2_NOP      = 3'd0,
                C2_RESPONSE = 3'd1,
                C2_READ     = 3'd2,
                C2_WRITE    = 3'd3;

    reg [CACHE_LINE_SIZE*8-1:0] storage [MEM_SIZE-1:0]; // 2^15 16-byte lines
    reg [BUS_SIZE-1:0] data_buff; // single bus

    reg [CACHE_OFFSET_SIZE-1:0] rwPosition; // ptr to next 2 bytes to read/write

    integer SEED = 225526;

    task delay;
        begin
            @(negedge clk);
        end
    endtask	

    always @(posedge clk or posedge reset) begin
        if (reset) begin
            for (int i = 0; i < 99; i=i+1) begin
                storage[i] = $random(SEED)>>16;
            end
            // $display("filled");

            data_buff = 'z;
            rwPosition = 0;
        end else begin
            if (command == C2_READ) begin
                // READ
                data_buff = storage[address][rwPosition*8 +: BUS_SIZE];
                rwPosition += 2;
            end else if (command == C2_WRITE) begin
                data_buff = 'z;
                // WRITE
                delay;
                for (int i=0; i<CACHE_LINE_SIZE/2; i=i+1) begin
                    storage[address][BUS_SIZE*i +: BUS_SIZE] = data;
                    delay;
                end
                // $display("after : %b", storage[address]);
                // rwPosition += 2;
            end else begin
                rwPosition = 0;
                data_buff = 'z;
            end
        end
    end

    assign data = data_buff;

endmodule

2-Lab/cache.sv
module cache#(
    parameter BUS_SIZE = 16 ,
    parameter MEM_ADDR_SIZE = 10 + 9,   // log2(MEM_SIZE)
    parameter CACHE_OFFSET_SIZE = 4,    // log2(CACHE_LINE_SIZE)
    parameter CACHE_LINE_SIZE   = 16
    ) (
    input clk,
    input reset,
    input [MEM_ADDR_SIZE-CACHE_OFFSET_SIZE-1:0] cpu_address,
    inout [BUS_SIZE-1:0] cpu_data,
    inout [3-1:0] cpu_command,

    output [MEM_ADDR_SIZE-CACHE_OFFSET_SIZE-1:0] mem_address,
    inout [BUS_SIZE-1:0] mem_data,
    output [2-1:0] mem_command
);

    parameter CACHE_WAY         = 2;

    parameter CACHE_LINE_COUNT  = 64;
    parameter CACHE_SETS_COUNT  = CACHE_LINE_COUNT/CACHE_WAY; 
    parameter CACHE_SIZE        = CACHE_LINE_COUNT * CACHE_LINE_SIZE;
   
    parameter CACHE_SET_SIZE    = 5;    // log2(CACHE_SETS_COUNT)
    parameter CACHE_TAG_SIZE    = 10;   // CACHE_LINE_SIZE - CACHE_SET_SIZE - CACHE_OFFSET_SIZE
    localparam  C1_NOP          = 3'd0,
                C1_READ8        = 3'd1,
                C1_READ16       = 3'd2,
                C1_READ32       = 3'd3,
                C1_INV_LINE     = 3'd4,
                C1_WRITE8       = 3'd5,
                C1_WRITE16      = 3'd6,
                C1_WRITE32_RESP = 3'd7;

    localparam  C2_NOP          = 2'd0,
                C2_RESPONSE     = 2'd1,
                C2_READ         = 2'd2,
                C2_WRITE        = 2'd3;

    // STORAGE
    reg valid_array [CACHE_SETS_COUNT-1:0][CACHE_WAY-1:0];
    reg dirty_array [CACHE_SETS_COUNT-1:0][CACHE_WAY-1:0];
    reg last_used_array [CACHE_SETS_COUNT-1:0]; // lRU
    reg [CACHE_TAG_SIZE-1:0] tag_array [CACHE_SETS_COUNT-1:0][CACHE_WAY-1:0];
    reg [CACHE_LINE_SIZE*8-1:0] data_array [CACHE_SETS_COUNT-1:0][CACHE_WAY-1:0]; // stores lines

    reg [MEM_ADDR_SIZE-1:0] cpu_address_buff;
    reg [CACHE_TAG_SIZE-1:0] cpu_tag_buff;
    reg [CACHE_SET_SIZE-1:0] cpu_set_buff;
    reg [CACHE_OFFSET_SIZE-1:0] cpu_offset_buff;
    reg [BUS_SIZE-1:0] cpu_data_bus_buff; // single bus
    reg [BUS_SIZE*2-1:0] cpu_data_to_write;
    reg [3-1:0] cpu_command_buff;
    
    reg [MEM_ADDR_SIZE-CACHE_OFFSET_SIZE-1:0] mem_address_buff;
    reg [CACHE_LINE_SIZE*8-1:0] mem_line_buff; // single line
    reg [BUS_SIZE-1:0] mem_data_buff;
    reg [2-1:0] mem_command_buff;

    task delay;
        begin
            @(negedge clk);
        end
    endtask	

    task replace_from_MM;
        // $display("replace_from_MM");
        // set
        mem_command_buff = C2_READ;
        delay;

        // read
        for (int i=0; i<CACHE_LINE_SIZE/2; i=i+1) begin
            mem_line_buff[BUS_SIZE*i +: BUS_SIZE] = mem_data;
            delay;
        end

        // restore
        mem_command_buff = 'z;
        
        // try to write in cache storage
        if (valid_array[cpu_set_buff][0] == 0) begin
            index_in_set = 0;
            // $display("store 0");
            store;
        end else if (valid_array[cpu_set_buff][1] == 0) begin
            index_in_set = 1;
            // $display("store 1");
            store;
        end else begin // evict
            // $display("eviction?");
            // LRU
            if (dirty_array[cpu_set_buff][last_used_array[cpu_set_buff]] == 1) begin
                // $display("eviction!");
                mem_address_buff[CACHE_TAG_SIZE+CACHE_SET_SIZE-1:CACHE_SET_SIZE] = tag_array[cpu_set_buff][last_used_array[cpu_set_buff]];
                mem_address_buff[CACHE_SET_SIZE-1:0] = cpu_set_buff;
                write_to_MM;
            end
            
            index_in_set = last_used_array[cpu_set_buff];
            store;
        end
    endtask 

    task write_to_MM;
        mem_command_buff = C2_WRITE;
        // $display("write_to_MM");
        delay;
        // write
        for (int i=0; i<CACHE_LINE_SIZE/2; i=i+1) begin
            mem_data_buff = data_array[cpu_set_buff][last_used_array[cpu_set_buff]][BUS_SIZE*i +: BUS_SIZE];
            // $display("2 %b", mem_data_buff);
            delay;
        end
        // restore
        mem_command_buff = C2_NOP;
        mem_data_buff = 'z;
    endtask

    reg index_in_set;
    task store;
        data_array[cpu_set_buff][index_in_set] = mem_line_buff;
        tag_array[cpu_set_buff][index_in_set] = cpu_tag_buff;
        dirty_array[cpu_set_buff][index_in_set] = 0;
        update_flags;
    endtask

    task update_flags;
        valid_array[cpu_set_buff][index_in_set] = 1;
        last_used_array[cpu_set_buff] = ~index_in_set; // opposite 
    endtask

    task read_cpu_address;
        mem_address_buff = cpu_address;
        cpu_tag_buff = cpu_address[CACHE_TAG_SIZE+CACHE_SET_SIZE-1:CACHE_SET_SIZE];
        cpu_set_buff = cpu_address[CACHE_SET_SIZE-1:0];

        delay;
        
        cpu_offset_buff = cpu_address[3:0];
    endtask

    reg [3-1:0] cur_cpu_command;
    task read_from_storage;
        if (cur_cpu_command == C1_READ8) begin
            cpu_data_bus_buff = data_array[cpu_set_buff][index_in_set][cpu_offset_buff*8 +: 8];
        end else if (cur_cpu_command == C1_READ16 || cur_cpu_command == C1_READ32) begin
            cpu_data_bus_buff = data_array[cpu_set_buff][index_in_set][cpu_offset_buff*8 +: 16];
        end
    endtask 

    task write_to_storage;
        if (cur_cpu_command == C1_WRITE8) begin
            data_array[cpu_set_buff][index_in_set][cpu_offset_buff*8 +: 8] = cpu_data_to_write;
        end else if (cur_cpu_command == C1_WRITE16) begin
            data_array[cpu_set_buff][index_in_set][cpu_offset_buff*8 +: 16] = cpu_data_to_write;
        end else if (cur_cpu_command == C1_WRITE32_RESP) begin
            data_array[cpu_set_buff][index_in_set][cpu_offset_buff*8 +: 32] = cpu_data_to_write;
        end
        dirty_array[cpu_set_buff][index_in_set] = 1;
        update_flags;
    endtask

    initial begin
        mem_line_buff     =  0;
        cpu_data_bus_buff = 'z;
        cpu_command_buff  = 'z;
        cur_cpu_command   =  0;
        mem_command_buff  = 'z;
        mem_data_buff     = 'z;
    end

    always @(posedge clk or posedge reset) begin
        if (reset) begin
            for (int i=0; i<CACHE_SETS_COUNT; i=i+1) begin
                valid_array[i][0] =  0;
                dirty_array[i][0] =  0;
                tag_array[i][0]   = 'z;
                data_array[i][0]  = 'z;
                valid_array[i][1] =  0;
                dirty_array[i][1] =  0;
                tag_array[i][1]   = 'z;
                data_array[i][1]  = 'z;
            end
        end 
        if (cpu_command == C1_READ8 || cpu_command == C1_READ16 || cpu_command == C1_READ32) begin
            // $display("C1_READX");
            cur_cpu_command = cpu_command;
            read_cpu_address;

            if (tag_array[cpu_set_buff][0] == cpu_tag_buff) begin
                if (valid_array[cpu_set_buff][0] == 1) begin
                    // $display("found 0");
                    index_in_set = 0;
                    read_from_storage;
                end
            end else if (tag_array[cpu_set_buff][1] == cpu_tag_buff) begin
                if (valid_array[cpu_set_buff][1] == 1) begin
                    // $display("found 1");
                    index_in_set = 1;
                    read_from_storage;
                end
            end else begin
                replace_from_MM;
                read_from_storage;
            end

            cpu_command_buff = C1_WRITE32_RESP;
            delay;

            if (cur_cpu_command == C1_READ32) begin
                delay;
                cpu_offset_buff += 2;
                read_from_storage;
                delay;
            end

            cpu_command_buff = 'z;
            cpu_data_bus_buff = 'z;
            cur_cpu_command = 'z;

        end else if (cpu_command == C1_WRITE8 || cpu_command == C1_WRITE16 || cpu_command == C1_WRITE32_RESP) begin
            // $display("C1_WRITEX");
            // $display("dirty: %b %b", dirty_array[cpu_set_buff][0], dirty_array[cpu_set_buff][1]);
            cur_cpu_command = cpu_command;
            cpu_data_to_write[0 +: BUS_SIZE] = cpu_data;
            read_cpu_address;
            if (cpu_command == C1_WRITE32_RESP) begin
                cpu_data_to_write[BUS_SIZE +: BUS_SIZE] = cpu_data;
            end

            if (tag_array[cpu_set_buff][0] == cpu_tag_buff) begin
                if (valid_array[cpu_set_buff][0] == 1) begin
                    // $display("found 0");
                    index_in_set = 0;
                    write_to_storage;
                end
            end else if (tag_array[cpu_set_buff][1] == cpu_tag_buff) begin
                if (valid_array[cpu_set_buff][1] == 1) begin
                    // $display("found 1");
                    index_in_set = 1;
                    write_to_storage;
                end
            end else begin
                replace_from_MM;
                write_to_storage;
            end
            // $display("dirty: %b %b", dirty_array[cpu_set_buff][0], dirty_array[cpu_set_buff][1]);
            cpu_command_buff = C1_WRITE32_RESP;
            delay;
            cpu_command_buff = 'z;
            cur_cpu_command = 'z;
        end
    end

    assign mem_address = mem_address_buff;
    assign mem_data = mem_data_buff;
    assign mem_command = mem_command_buff;
    assign cpu_data = cpu_data_bus_buff;
    assign cpu_command = cpu_command_buff;

endmodule

2-Lab/cpu.sv
module cpu #(
    parameter MEM_ADDR_SIZE = 10 + 9, 
    parameter BUS_SIZE = 16,
    parameter CACHE_OFFSET_SIZE = 4
    ) (

    input clk,
    output [MEM_ADDR_SIZE-CACHE_OFFSET_SIZE-1:0] address,
    inout [BUS_SIZE-1:0] data,
    inout [3-1:0] command
);

    localparam  C1_NOP          = 3'd0,
                C1_READ8        = 3'd1,
                C1_READ16       = 3'd2,
                C1_READ32       = 3'd3,
                C1_INV_LINE     = 3'd4,
                C1_WRITE8       = 3'd5,
                C1_WRITE16      = 3'd6,
                C1_WRITE32_RESP = 3'd7;
    
    reg [MEM_ADDR_SIZE-1:0] cpu_address_buff;
    reg [MEM_ADDR_SIZE-CACHE_OFFSET_SIZE-1:0] address_bus_buff;
    reg [BUS_SIZE*2-1:0] data_to_write; 
    reg [BUS_SIZE-1:0] data_buff;
    reg [3-1:0] cpu_command_buff;
    reg [BUS_SIZE-1:0] recieved_data;
    reg [BUS_SIZE*2-1:0] local_storage;

    task delay;
        begin
            @(negedge clk);
        end
    endtask	
    
    task send_address;
        address_bus_buff = cpu_address_buff[MEM_ADDR_SIZE-1:CACHE_OFFSET_SIZE];
        delay;
        address_bus_buff = cpu_address_buff[CACHE_OFFSET_SIZE-1:0];
        delay;
    endtask

    task wait_for_resp;
        while (command !== C1_WRITE32_RESP) begin 
            delay;
        end
    endtask

    task READ8;
        cpu_command_buff = C1_READ8;
        READ;
        local_storage = recieved_data;
    endtask
    task READ16;
        cpu_command_buff = C1_READ16;
        READ;
        local_storage = recieved_data;
    endtask
    task READ32;
        cpu_command_buff = C1_READ32;
        READ;
        local_storage[BUS_SIZE-1:0] = recieved_data;
        READ;
        local_storage[BUS_SIZE*2-1:BUS_SIZE] = recieved_data;
        
    endtask

    task READ;
        send_address;
        cpu_command_buff = 'z;
        wait_for_resp;
        recieved_data = data;
    endtask

    task WRITE8;
        cpu_command_buff = C1_WRITE8;
        WRITE;
    endtask
    task WRITE16;
        cpu_command_buff = C1_WRITE16;
        WRITE;
    endtask
    task WRITE32;
        cpu_command_buff = C1_WRITE32_RESP;

        data_buff = data_to_write[BUS_SIZE-1:0];
        address_bus_buff = cpu_address_buff[MEM_ADDR_SIZE-1:CACHE_OFFSET_SIZE];
        delay;

        data_buff = data_to_write[BUS_SIZE*2-1:BUS_SIZE];
        address_bus_buff = cpu_address_buff[CACHE_OFFSET_SIZE-1:0];
        delay;

        cpu_command_buff = 'z;
        wait_for_resp;
        data_buff = 'z;
    endtask

    task WRITE;
        data_buff = data_to_write;
        send_address;
        cpu_command_buff = 'z;
        wait_for_resp;
        data_buff = 'z;
    endtask

    initial begin
        address_bus_buff = 'z;
        cpu_command_buff = 'z;
        recieved_data = 0;
        data_buff = 'z;
    end

    task read_write_test;
        $display("----------------");
        $display("#############  READ32/WRITE32 TEST  #############");
        $display("----------------");

        cpu_address_buff = 19'b0000000000_01010_0000;
        $display("read from %b", cpu_address_buff);
        READ32;
        $display("data      %b", local_storage);
        $display("----------------");

        cpu_address_buff = 19'b0000000000_01010_0000;
        data_to_write = 32'b0101_0101_0101_0101_0101_0101_0101_0101;
        $display("write to  %b", cpu_address_buff);
        $display("data      %b", data_to_write);
        WRITE32;
        $display("----------------");
       
        cpu_address_buff = 19'b0000000000_01010_0000;
        $display("read from %b", cpu_address_buff);
        READ32;
        $display("data      %b", local_storage);
        $display("----------------");

        cpu_address_buff = 19'b0000000000_01010_0000;
        data_to_write = 32'b1111_1111_1111_1111_0000_0000_0000_0000;
        $display("write to  %b", cpu_address_buff);
        $display("data      %b", data_to_write);
        WRITE32;
        $display("----------------");
        
        cpu_address_buff = 19'b0000000000_01010_0000;
        $display("read from %b", cpu_address_buff);
        READ32;
        $display("data      %b", local_storage);
        $display("----------------");
    endtask

    task eviction_test;
        $display("\n###########################################");
        $display("#############  EVICTION TEST  #############");
        $display("###########################################\n");

        $display("~~~~~~~~~~~~~");
        $display("~~~ FIRST ~~~");
        $display("~~~~~~~~~~~~~");
        $display("----------------");
        cpu_address_buff = 19'b0000000000_01110_0000;
        $display("read from %b", cpu_address_buff);
        READ32;
        $display("data      %b", local_storage);
        $display("----------------");

        cpu_address_buff = 19'b0000000000_01110_0000;
        data_to_write = 32'b1111_0000_1111_0000_0000_1111_0000_1111;
        $display("write to  %b", cpu_address_buff);
        $display("data      %b", data_to_write);
        WRITE32;
        $display("----------------");

        cpu_address_buff = 19'b0000000000_01110_0000;
        $display("read from %b", cpu_address_buff);
        READ32;
        $display("data      %b", local_storage);
        $display("----------------\n");

        $display("~~~~~~~~~~~~~~");
        $display("~~~ SECOND ~~~");
        $display("~~~~~~~~~~~~~~");
        $display("----------------");
        cpu_address_buff = 19'b0000000001_01110_0000;
        $display("read from %b", cpu_address_buff);
        READ32;
        $display("data      %b", local_storage);
        $display("----------------");

        cpu_address_buff = 19'b0000000001_01110_0000;
        data_to_write = 32'b1111_1111_1111_1111_0000_1111_1111_0000;
        $display("write to  %b", cpu_address_buff);
        $display("data      %b", data_to_write);
        WRITE32;
        $display("----------------");

        cpu_address_buff = 19'b0000000001_01110_0000;
        $display("read from %b", cpu_address_buff);
        READ32;
        $display("data      %b", local_storage);
        $display("----------------\n");

        $display("~~~~~~~~~~~~~~~~~");
        $display("~~~ EVICTION! ~~~");
        $display("~~~~~~~~~~~~~~~~~");
        $display("----------------");
        cpu_address_buff = 19'b0000000010_01110_0000;
        $display("read from %b", cpu_address_buff);
        READ32;
        $display("data      %b", local_storage);
        $display("----------------");

        cpu_address_buff = 19'b0000000010_01110_0000;
        data_to_write = 32'b1111_1111_0001_1001_1001_1000_1111_1111;
        $display("write to  %b", cpu_address_buff);
        $display("data      %b", data_to_write);
        WRITE32;
        $display("----------------");

        cpu_address_buff = 19'b0000000010_01110_0000;
        $display("read from %b", cpu_address_buff);
        READ32;
        $display("data      %b", local_storage);
        $display("----------------\n");

        $display("~~~~~~~~~~~~~~~~~~~");
        $display("~~~ FIRST AGAIN ~~~");
        $display("~~~~~~~~~~~~~~~~~~~");
        $display("----------------");
        cpu_address_buff = 19'b0000000000_01110_0000;
        $display("read from %b", cpu_address_buff);
        READ32;
        $display("data      %b", local_storage);
        $display("----------------");
    endtask

    // Place for test calls
    initial begin
        delay;
        
        eviction_test;

        $finish();
    end

    assign address = address_bus_buff;
    assign data = data_buff;
    assign command = cpu_command_buff;
    
endmodule

2-Lab/testbench.sv
module testbench ();
    parameter BUS_SIZE = 16 ;
    parameter MEM_ADDR_SIZE = 10 + 9;   // log2(MEM_SIZE)
    parameter CACHE_OFFSET_SIZE = 4;    // log2(CACHE_LINE_SIZE)
    parameter CACHE_LINE_SIZE = 16;
    wire [MEM_ADDR_SIZE-CACHE_OFFSET_SIZE-1:0] cpu_address;
    wire [BUS_SIZE-1:0] cpu_data;
    wire [3-1:0] cpu_command;
    wire [MEM_ADDR_SIZE-CACHE_OFFSET_SIZE-1:0] mem_address;
    wire [BUS_SIZE-1:0] mem_data;
    wire [2-1:0] mem_command;

    reg clk;
    reg reset;


    cpu #(MEM_ADDR_SIZE, BUS_SIZE, CACHE_OFFSET_SIZE) 
    cpu (clk, cpu_address, cpu_data, cpu_command);

    cache #(BUS_SIZE, MEM_ADDR_SIZE, CACHE_OFFSET_SIZE, CACHE_LINE_SIZE)
    cache (clk, reset, 
    cpu_address, cpu_data, cpu_command,
    mem_address, mem_data, mem_command);

    mem #(MEM_ADDR_SIZE, BUS_SIZE, CACHE_OFFSET_SIZE, CACHE_LINE_SIZE) 
    mem(clk, reset, mem_address, mem_data, mem_command);

     task delay;
        begin
            @(negedge clk);
        end
    endtask	

    initial begin
        reset = 0;
        #1 reset = 1;
        #1 reset = 0;
        clk = 1'd0;

        forever begin
            #1 clk = ~clk;
            // $display("addr: %b", mem_address);
            // $display("data: %b", mem_data);
            // $display("cache.: %b", cache.mem_data_buff);
            // $display("mem.: %b", mem.data_buff);
            // $display("command: %b", mem_command);
        end
    end

    initial begin
        $dumpfile("dump_cache.vcd"); 
        $dumpvars;
    end

endmodule

2-Lab/dump_cache.vcd
$date
	Wed Nov 30 23:49:13 2022
$end
$version
	Icarus Verilog
$end
$timescale
	1s
$end
$scope module testbench $end
$var wire 3 ! cpu_command [2:0] $end
$var wire 16 " cpu_data [15:0] $end
$var wire 16 # mem_data [15:0] $end
$var wire 2 $ mem_command [1:0] $end
$var wire 15 % mem_address [14:0] $end
$var wire 15 & cpu_address [14:0] $end
$var reg 1 ' clk $end
$var reg 1 ( reset $end
$scope module cache $end
$var wire 1 ' clk $end
$var wire 3 ) cpu_command [2:0] $end
$var wire 16 * cpu_data [15:0] $end
$var wire 15 + mem_address [14:0] $end
$var wire 2 , mem_command [1:0] $end
$var wire 16 - mem_data [15:0] $end
$var wire 1 ( reset $end
$var wire 15 . cpu_address [14:0] $end
$var reg 3 / cpu_command_buff [2:0] $end
$var reg 16 0 cpu_data_bus_buff [15:0] $end
$var reg 32 1 cpu_data_to_write [31:0] $end
$var reg 4 2 cpu_offset_buff [3:0] $end
$var reg 5 3 cpu_set_buff [4:0] $end
$var reg 10 4 cpu_tag_buff [9:0] $end
$var reg 3 5 cur_cpu_command [2:0] $end
$var reg 1 6 index_in_set $end
$var reg 15 7 mem_address_buff [14:0] $end
$var reg 2 8 mem_command_buff [1:0] $end
$var reg 16 9 mem_data_buff [15:0] $end
$var reg 128 : mem_line_buff [127:0] $end
$scope begin $ivl_for_loop2 $end
$var integer 32 ; i [31:0] $end
$upscope $end
$scope task delay $end
$upscope $end
$scope task read_cpu_address $end
$upscope $end
$scope task read_from_storage $end
$upscope $end
$scope task replace_from_MM $end
$scope begin $ivl_for_loop0 $end
$var integer 32 < i [31:0] $end
$upscope $end
$upscope $end
$scope task store $end
$upscope $end
$scope task update_flags $end
$upscope $end
$scope task write_to_MM $end
$scope begin $ivl_for_loop1 $end
$var integer 32 = i [31:0] $end
$upscope $end
$upscope $end
$scope task write_to_storage $end
$upscope $end
$upscope $end
$scope module cpu $end
$var wire 15 > address [14:0] $end
$var wire 1 ' clk $end
$var wire 3 ? command [2:0] $end
$var wire 16 @ data [15:0] $end
$var reg 15 A address_bus_buff [14:0] $end
$var reg 19 B cpu_address_buff [18:0] $end
$var reg 3 C cpu_command_buff [2:0] $end
$var reg 16 D data_buff [15:0] $end
$var reg 32 E data_to_write [31:0] $end
$var reg 32 F local_storage [31:0] $end
$var reg 16 G recieved_data [15:0] $end
$scope task READ $end
$upscope $end
$scope task READ16 $end
$upscope $end
$scope task READ32 $end
$upscope $end
$scope task READ8 $end
$upscope $end
$scope task WRITE $end
$upscope $end
$scope task WRITE16 $end
$upscope $end
$scope task WRITE32 $end
$upscope $end
$scope task WRITE8 $end
$upscope $end
$scope task delay $end
$upscope $end
$scope task eviction_test $end
$upscope $end
$scope task read_write_test $end
$upscope $end
$scope task send_address $end
$upscope $end
$scope task wait_for_resp $end
$upscope $end
$upscope $end
$scope module mem $end
$var wire 15 H address [14:0] $end
$var wire 1 ' clk $end
$var wire 2 I command [1:0] $end
$var wire 16 J data [15:0] $end
$var wire 1 ( reset $end
$var reg 16 K data_buff [15:0] $end
$var reg 4 L rwPosition [3:0] $end
$var integer 32 M SEED [31:0] $end
$scope begin $ivl_for_loop3 $end
$var integer 32 N i [31:0] $end
$upscope $end
$scope begin $ivl_for_loop4 $end
$var integer 32 O i [31:0] $end
$upscope $end
$scope task delay $end
$upscope $end
$upscope $end
$scope task delay $end
$upscope $end
$upscope $end
$enddefinitions $end
#0
$dumpvars
b0 O
b0 N
b110111000011110110 M
bx L
bx K
bx J
bz I
bx H
b0 G
bx F
bx E
bz D
bz C
bx B
bz A
bz @
bz ?
bz >
b0 =
b0 <
b0 ;
b0 :
bz 9
bz 8
bx 7
x6
b0 5
bx 4
bx 3
bx 2
bx 1
bz 0
bz /
bz .
bx -
bz ,
bx +
bz *
bz )
0(
x'
bz &
bx %
bz $
bx #
bz "
bz !
$end
#1
b0 L
bz #
bz -
bz J
bz K
b1100011 N
b110000110000011110001000101 M
b100000 ;
1(
#2
b1110 &
b1110 .
b1110 >
b1110 A
b11 !
b11 )
b11 ?
b11 C
b11100000 B
0'
0(
#3
b1110 3
b0 4
b1110 %
b1110 +
b1110 H
b1110 7
b11 5
1'
#4
b10 $
b10 ,
b10 I
b10 8
b0 2
b0 &
b0 .
b0 >
b0 A
0'
#5
b10 L
b1001110001110100 #
b1001110001110100 -
b1001110001110100 J
b1001110001110100 K
1'
#6
b1001110001110100 :
bz !
bz )
bz ?
bz C
0'
#7
b100 L
b1111111111111111 #
b1111111111111111 -
b1111111111111111 J
b1111111111111111 K
1'
#8
b11111111111111111001110001110100 :
b1 <
0'
#9
b110 L
1'
#10
b111111111111111111111111111111111001110001110100 :
b10 <
0'
#11
b1000 L
1'
#12
b1111111111111111111111111111111111111111111111111001110001110100 :
b11 <
0'
#13
b1010 L
1'
#14
b11111111111111111111111111111111111111111111111111111111111111111001110001110100 :
b100 <
0'
#15
b1100 L
1'
#16
b111111111111111111111111111111111111111111111111111111111111111111111111111111111001110001110100 :
b101 <
0'
#17
b1110 L
1'
#18
b1111111111111111111111111111111111111111111111111111111111111111111111111111111111111111111111111001110001110100 :
b110 <
0'
#19
b0 L
b0 #
b0 -
b0 J
b0 K
1'
#20
b111 <
0'
#21
b10 L
b1001110001110100 #
b1001110001110100 -
b1001110001110100 J
b1001110001110100 K
1'
#22
b111 !
b111 )
b111 ?
b111 /
b1001110001110100 "
b1001110001110100 *
b1001110001110100 @
b1001110001110100 0
06
bz $
bz ,
bz I
bz 8
b1000 <
0'
#23
bz #
bz -
bz J
bz K
b0 L
1'
#24
b1110 &
b1110 .
b1110 >
b1110 A
bx1001110001110100 F
b1001110001110100 G
0'
#25
1'
#26
b1111111111111111 "
b1111111111111111 *
b1111111111111111 @
b1111111111111111 0
b10 2
b0 &
b0 .
b0 >
b0 A
0'
#27
1'
#28
bz 5
bz 0
bz /
b1110 &
b1110 .
b1110 >
b1110 A
b111100001111 "
b111100001111 *
b111100001111 @
b111100001111 D
b111 C
b11110000111100000000111100001111 E
b11111111111111111001110001110100 F
b1111111111111111 G
0'
#29
bx0000111100001111 1
b111 5
1'
#30
b111 /
b11110000111100000000111100001111 1
b0 2
b0 &
b0 .
b0 >
b0 A
b1111000011110000 "
b1111000011110000 *
b1111000011110000 @
b1111000011110000 D
0'
#31
1'
#32
bz 5
bz /
b1110 &
b1110 .
b1110 >
b1110 A
b11 !
b11 )
b11 ?
bz "
bz *
bz @
bz D
b11 C
0'
#33
b11 5
1'
#34
bx11 !
bx11 )
bx11 ?
b111 /
b111100001111 "
b111100001111 *
b111100001111 @
b111100001111 0
b0 &
b0 .
b0 >
b0 A
0'
#35
1'
#36
b1110 &
b1110 .
b1110 >
b1110 A
b11111111111111110000111100001111 F
b111100001111 G
b111 !
b111 )
b111 ?
bz C
0'
#37
1'
#38
b1111000011110000 "
b1111000011110000 *
b1111000011110000 @
b1111000011110000 0
b10 2
b0 &
b0 .
b0 >
b0 A
0'
#39
1'
#40
bz 5
bz "
bz *
bz @
bz 0
bz /
b101110 &
b101110 .
b101110 >
b101110 A
b11 !
b11 )
b11 ?
b11 C
b1011100000 B
b11110000111100000000111100001111 F
b1111000011110000 G
0'
#41
b1 4
b101110 %
b101110 +
b101110 H
b101110 7
b11 5
1'
#42
b10 $
b10 ,
b10 I
b10 8
b0 2
b0 &
b0 .
b0 >
b0 A
0'
#43
b10 L
b1001111111010111 #
b1001111111010111 -
b1001111111010111 J
b1001111111010111 K
1'
#44
b1111111111111111111111111111111111111111111111111111111111111111111111111111111111111111111111111001111111010111 :
b0 <
bz !
bz )
bz ?
bz C
0'
#45
b100 L
b1111111111111111 #
b1111111111111111 -
b1111111111111111 J
b1111111111111111 K
1'
#46
b1 <
0'
#47
b110 L
1'
#48
b10 <
0'
#49
b1000 L
1'
#50
b11 <
0'
#51
b1010 L
1'
#52
b100 <
0'
#53
b1100 L
1'
#54
b101 <
0'
#55
b1110 L
1'
#56
b110 <
0'
#57
b0 L
b0 #
b0 -
b0 J
b0 K
1'
#58
b111 <
0'
#59
b10 L
b1001111111010111 #
b1001111111010111 -
b1001111111010111 J
b1001111111010111 K
1'
#60
b111 !
b111 )
b111 ?
b111 /
b1001111111010111 "
b1001111111010111 *
b1001111111010111 @
b1001111111010111 0
16
bz $
bz ,
bz I
bz 8
b1000 <
0'
#61
bz #
bz -
bz J
bz K
b0 L
1'
#62
b101110 &
b101110 .
b101110 >
b101110 A
b11110000111100001001111111010111 F
b1001111111010111 G
0'
#63
1'
#64
b1111111111111111 "
b1111111111111111 *
b1111111111111111 @
b1111111111111111 0
b10 2
b0 &
b0 .
b0 >
b0 A
0'
#65
1'
#66
bz 5
bz 0
bz /
b101110 &
b101110 .
b101110 >
b101110 A
b111111110000 "
b111111110000 *
b111111110000 @
b111111110000 D
b111 C
b11111111111111110000111111110000 E
b11111111111111111001111111010111 F
b1111111111111111 G
0'
#67
b11110000111100000000111111110000 1
b111 5
1'
#68
b111 /
b11111111111111110000111111110000 1
b0 2
b0 &
b0 .
b0 >
b0 A
b1111111111111111 "
b1111111111111111 *
b1111111111111111 @
b1111111111111111 D
0'
#69
1'
#70
bz 5
bz /
b101110 &
b101110 .
b101110 >
b101110 A
b11 !
b11 )
b11 ?
bz "
bz *
bz @
bz D
b11 C
0'
#71
b11 5
1'
#72
bx11 !
bx11 )
bx11 ?
b111 /
b111111110000 "
b111111110000 *
b111111110000 @
b111111110000 0
b0 &
b0 .
b0 >
b0 A
0'
#73
1'
#74
b101110 &
b101110 .
b101110 >
b101110 A
b11111111111111110000111111110000 F
b111111110000 G
b111 !
b111 )
b111 ?
bz C
0'
#75
1'
#76
b1111111111111111 "
b1111111111111111 *
b1111111111111111 @
b1111111111111111 0
b10 2
b0 &
b0 .
b0 >
b0 A
0'
#77
1'
#78
bz 5
bz "
bz *
bz @
bz 0
bz /
b1001110 &
b1001110 .
b1001110 >
b1001110 A
b11 !
b11 )
b11 ?
b11 C
b10011100000 B
b1111111111111111 G
0'
#79
b10 4
b1001110 %
b1001110 +
b1001110 H
b1001110 7
b11 5
1'
#80
b10 $
b10 ,
b10 I
b10 8
b0 2
b0 &
b0 .
b0 >
b0 A
0'
#81
b10 L
b110110000111 #
b110110000111 -
b110110000111 J
b110110000111 K
1'
#82
b1111111111111111111111111111111111111111111111111111111111111111111111111111111111111111111111110000110110000111 :
b0 <
bz !
bz )
bz ?
bz C
0'
#83
b100 L
b0 #
b0 -
b0 J
b0 K
1'
#84
b1111111111111111111111111111111111111111111111111111111111111111111111111111111100000000000000000000110110000111 :
b1 <
0'
#85
b110 L
1'
#86
b1111111111111111111111111111111111111111111111111111111111111111000000000000000000000000000000000000110110000111 :
b10 <
0'
#87
b1000 L
1'
#88
b1111111111111111111111111111111111111111111111110000000000000000000000000000000000000000000000000000110110000111 :
b11 <
0'
#89
b1010 L
1'
#90
b1111111111111111111111111111111100000000000000000000000000000000000000000000000000000000000000000000110110000111 :
b100 <
0'
#91
b1100 L
1'
#92
b1111111111111111000000000000000000000000000000000000000000000000000000000000000000000000000000000000110110000111 :
b101 <
0'
#93
b1110 L
1'
#94
b110110000111 :
b110 <
0'
