2-Lab/mem.sv
module mem #(
    parameter MEM_ADDR_SIZE = 10 + 9, 
    parameter CACHE_OFFSET_SIZE = 4,
    parameter BUS_SIZE = 16,
    parameter CACHE_LINE_SIZE = 16
    ) (
    input clk,

    input [MEM_ADDR_SIZE-CACHE_OFFSET_SIZE-1:0] address,
    output [BUS_SIZE-1:0] data,
    input [2-1:0] command,
    input reset
);
    parameter MEM_SIZE = 1 << (MEM_ADDR_SIZE-CACHE_OFFSET_SIZE);   // 512KB = 2^9 * 2^10 = 2^19

    localparam  C2_NOP      = 3'd0,
                C2_RESPONSE = 3'd1,
                C2_READ     = 3'd2,
                C2_WRITE    = 3'd3;

    reg [CACHE_LINE_SIZE*8-1:0] storage [MEM_SIZE-1:0]; // 2^15 16-byte lines
    reg [BUS_SIZE-1:0] data_buff; // single bus
    reg [2-1:0] command_buff;

    reg [CACHE_OFFSET_SIZE-1:0] rwPosition; // ptr to next 2 bytes to read/write

    integer SEED = 225526;

    always @(posedge clk or posedge reset) begin
        if (reset) begin
            for (int i = 0; i < MEM_SIZE; i=i+1) begin
                storage[i] = i;//$random(SEED)>>16;
            end
            $display("filled");

            data_buff = 0;
            command_buff = 0;
            rwPosition = 0;
        end else begin
            command_buff = 0;
            if (command == C2_READ) begin
                // READ
                for (int i=0; i<CACHE_LINE_SIZE; i=i+1) begin
                    data_buff[i] = storage[address][rwPosition*8 + i];
                end
                rwPosition += 2;
            end else if (command == C2_WRITE) begin
                // WRITE
                for (int i=0; i<CACHE_LINE_SIZE; i=i+1) begin
                    storage[address + (i << CACHE_OFFSET_SIZE)] = data[i];
                end
                command_buff = 1;
            end else begin
                rwPosition = 0;
            end
        end
    end
    // assign command = command_buff;
    assign data = data_buff;
endmodule

2-Lab/cache.sv
module cache (
    // input clk;

    // inout [MEM_ADDR_SIZE-1:0] cpu_address,
    // inout [BUS_SIZE-1:0] cpu_data,
    // inout [3-1:0] cpu_command,

    inout [MEM_ADDR_SIZE-CACHE_OFFSET_SIZE-1:0] mem_address,
    inout [BUS_SIZE-1:0] mem_data,
    inout [2-1:0] mem_command
    );

    // TEMP
    parameter BUS_SIZE = 16;

    parameter MEM_ADDR_SIZE = 10 + 9;          // log2(MEM_SIZE)
    parameter CACHE_WAY         = 2;
    parameter CACHE_LINE_SIZE   = 16;
    parameter CACHE_LINE_COUNT  = 64;
    parameter CACHE_SIZE        = CACHE_LINE_COUNT * CACHE_LINE_SIZE;

    parameter CACHE_OFFSET_SIZE = 4;    // log2(CACHE_LINE_SIZE)
    parameter CACHE_SET_SIZE    = 5;    // log2(CACHE_LINE_COUNT/CACHE_WAY)
    parameter CACHE_TAG_SIZE    = 10;   // CACHE_LINE_SIZE - CACHE_SET_SIZE - CACHE_OFFSET_SIZE

    localparam  C1_NOP      = 3'd0;
    localparam  C1_READ8    = 3'd1;
    localparam  C1_READ16   = 3'd2,
                C1_READ32   = 3'd3,
                C1_INV_LINE = 3'd4,
                C1_WRITE8   = 3'd5,
                C1_WRITE16  = 3'd6,
                C1_WRITE32  = 3'd7;

    localparam  C2_NOP      = 2'd0,
                C2_RESPONSE = 2'd1,
                C2_READ     = 2'd2,
                C2_WRITE    = 2'd3;

    // localparam  IDLE        = 3'd0,
    //             READ        = 3'd1,
    //             WRITE       = 3'd2,
    //             READMM      = 3'd3,
    //             WAITFORMM   = 3'd4,
    //             UPDATEMM    = 3'd5,
    //             UPDATECACHE = 3'd6;

    // reg [3-1:0] state;

    // STORAGE
    // reg valid_array [CACHE_SET_SIZE-1:0][CACHE_WAY-1:0];
    // reg dirty_array [CACHE_SET_SIZE-1:0][CACHE_WAY-1:0];
    // reg last_used_array [CACHE_SET_SIZE-1:0][CACHE_WAY-1:0]; // lRU
    // reg [CACHE_TAG_SIZE-1:0] tag_array [CACHE_SET_SIZE-1:0][CACHE_WAY-1:0];
    // reg [CACHE_LINE_SIZE*8-1:0] data_array [CACHE_SET_SIZE-1:0][CACHE_WAY-1:0]; // stores lines

    // reg [MEM_ADDR_SIZE-1:0] cpu_address_buff,
    // reg [CACHE_LINE_SIZE*8-1:0] cpu_data_buff; // single line
    // reg [3-1:0] cpu_command_buff;
    
    reg [MEM_ADDR_SIZE-CACHE_OFFSET_SIZE-1:0] mem_address_buff;
    reg [CACHE_LINE_SIZE*8-1:0] mem_line_buff; // single line
    reg [BUS_SIZE-1:0] mem_data_buff;
    reg [2-1:0] mem_command_buff;

    // integer bitOfOp;

    reg clk;
    reg reset = 0;

    mem #(MEM_ADDR_SIZE, CACHE_OFFSET_SIZE, BUS_SIZE, CACHE_LINE_SIZE) 
    m1(clk, mem_address_buff, mem_data_buff, mem_command_buff, reset);

	initial begin
        clk = 1'd0;
        forever
            #1 clk = ~clk;
    end
    
    task delay;
        begin
            @(negedge clk);
        end
    endtask	

    initial begin
        $dumpfile("dump_cache.vcd"); 
        $dumpvars;

        reset = 0;
        #1 reset = 1;
        #1 reset = 0;
        delay;


        mem_address_buff = 15'b000000000000000;

        repeat(32) begin
            mem_line_buff = 0;
            mem_command_buff = C2_NOP;
            delay;
            mem_command_buff = C2_READ;
            delay;
            for (int i=0; i<CACHE_LINE_SIZE/2; i=i+1) begin
                mem_line_buff[BUS_SIZE*i +: BUS_SIZE] = mem_data_buff;
                delay;
            end
            $display ("%0d mem_line_buff = %b", mem_address_buff, mem_line_buff);
            mem_address_buff += 1;
        end


        // mem_address_buff = 15'd30;
        // mem_line_buff = 0;
        // mem_command_buff = C2_NOP;
        // delay;

        // mem_command_buff = C2_READ;
        // delay;

        // for (int i=0; i<CACHE_LINE_SIZE/2; i=i+1) begin
        //     mem_line_buff[BUS_SIZE*i +: BUS_SIZE] = mem_data_buff;
        //     delay;
        // end

        // $display ("mem_line_buff = %b", mem_line_buff);


        // $display("%b", mem_line_buff);
        $finish();
    end

    // always @(posedge clk) begin
    //     case(state)
    //         IDLE: begin
    //             case (cpu_command)
    //                 C1_NOP: begin
                        
    //                 end
    //                 C1_READ8: begin
    //                     state = READ;
    //                     mem_address_buff = cpu_address;
    //                     bitOfOp = 8;
    //                 end
    //                 C1_READ16: begin
                        
    //                     bitOfOp = 16;
    //                 end
    //                 C1_READ32: begin
                        
    //                     bitOfOp = 32;
    //                 end
    //                 C1_INV_LINE: begin
                        
    //                 end
    //                 C1_WRITE8: begin
                        
    //                     bitOfOp = 8;
    //                 end
    //                 C1_WRITE16: begin
                        
    //                     bitOfOp = 16;
    //                 end
    //                 C1_WRITE32: begin
                        
    //                     bitOfOp = 32;
    //                 end
    //             endcase
    //         end
    //         READ: begin
    //             reg [CACHE_SET_SIZE-1:0] set = cpu_address >> CACHE_OFFSET_SIZE;
    //             reg [CACHE_TAG_SIZE-1:0] tag = cpu_address >> (CACHE_SET_SIZE + CACHE_OFFSET_SIZE);

    //             if (valid_array[set][0] == 1 && tag_array[set][0] == tag) begin

    //             end else if (valid_array[set][1] == 1 && tag_array[set][1] == tag) begin
                    
    //             end else begin
    //                 // miss
    //                 if (dirty_array[set][last_used_array[set]] == 1) begin
    //                     // UPDATEMM
    //                     // dirty
    //                     // flag
    //                 end else begin
    //                     // READMM
    //                 end
    //             end

    //             assign hit_w0 = vw0 & (tagdata == rtag0[10:0]);
    //             assign hit_w1 = vw1 & (tagdata == rtag1[10:0]);
    //             assign hit = hit_w0 | hit_w1;
    //         end
    //         WRITE: begin
                
    //         end
    //         READMM: begin
                
    //         end
    //         WAITFORMM: begin
                
    //         end
    //         UPDATEMM: begin
                
    //         end
    //         UPDATECACHE: begin
                
    //         end
    //     endcase
    // end

    // assign mem_address = mem_address_buff;

    // // CPU
    // always @(posedge clk) begin
    //     mem_command_buff = 0;
    //     // C1_READ8
    //     if (cpu_command == 3) begin
    //         reg [CACHE_SET_SIZE-1:0] set = cpu_address >> CACHE_OFFSET_SIZE;
    //         reg [CACHE_TAG_SIZE-1:0] tag = cpu_address >> (CACHE_SET_SIZE + CACHE_OFFSET_SIZE);
    //         reg found = 0;
    //         for (int i=0; i<CACHE_SET_SIZE; i=i+1) begin
    //             if (tag_array[set][i] == tag) begin
    //                 // Retrurn data
    //                 cpu_data_buff = data_array[set][i];
    //                 cpu_command_buff = 7;
    //             end
    //         end

    //         if (found == 0) begin 
    //             // Request from mem
    //             // Set valid 
    //             valid_array[set][i] = 1;
    //         end

    //     end
    // end
    // assign mem_command = mem_command_buff;
    // assign mem_data = mem_line_buff;

    // // MEM
    // always @(posedge clk) begin
    //     cpu_command_buff = 0;
    //     // C2_READ
    //     if (mem_command == 1) begin
    //         reg [CACHE_SET_SIZE-1:0] set = mem_address >> CACHE_OFFSET_SIZE;
    //         reg [CACHE_TAG_SIZE-1:0] tag = mem_address >> (CACHE_SET_SIZE + CACHE_OFFSET_SIZE);
    //         reg found = 0;
    //         for (int i=0; i<CACHE_SET_SIZE; i=i+1) begin
    //             if (valid_array[set][i] == 0) begin
    //                 found = 1;
    //                 valid_array[set][i] = 1;
    //                 dirty_array[set][i] = 0;
    //                 tag_array[set][i] = tag;
    //                 data_array[set][i] = mem_data;
    //             end
    //         end
    //         if (found == 0) begin
    //             // search for not dirty
    //             // if all dirty write one and replace with new data
    //         end
    //         cpu_data_buff = mem_data;

    //         cpu_command_buff = 7;
    //     end
    // end
    // assign cpu_command = cpu_command_buff;
    // assign cpu_data = cpu_data_buff;

    

endmodule

2-Lab/dump_cache.vcd
$date
	Tue Nov 29 00:04:49 2022
$end
$version
	Icarus Verilog
$end
$timescale
	1s
$end
$scope module cache $end
$var wire 15 ! mem_address [14:0] $end
$var wire 2 " mem_command [1:0] $end
$var wire 16 # mem_data [15:0] $end
$var wire 16 $ mem_data_buff [15:0] $end
$var reg 1 % clk $end
$var reg 15 & mem_address_buff [14:0] $end
$var reg 2 ' mem_command_buff [1:0] $end
$var reg 128 ( mem_line_buff [127:0] $end
$var reg 1 ) reset $end
$scope module m1 $end
$var wire 15 * address [14:0] $end
$var wire 1 % clk $end
$var wire 2 + command [1:0] $end
$var wire 16 , data [15:0] $end
$var wire 1 ) reset $end
$var reg 2 - command_buff [1:0] $end
$var reg 16 . data_buff [15:0] $end
$var reg 4 / rwPosition [3:0] $end
$var integer 32 0 SEED [31:0] $end
$scope begin $ivl_for_loop1 $end
$var integer 32 1 i [31:0] $end
$upscope $end
$scope begin $ivl_for_loop2 $end
$var integer 32 2 i [31:0] $end
$upscope $end
$scope begin $ivl_for_loop3 $end
$var integer 32 3 i [31:0] $end
$upscope $end
$upscope $end
$scope begin $ivl_for_loop0 $end
$var integer 32 4 i [31:0] $end
$upscope $end
$scope task delay $end
$upscope $end
$upscope $end
$enddefinitions $end
#0
$dumpvars
b0 4
b0 3
b0 2
b0 1
b110111000011110110 0
bx /
bx .
bx -
bx ,
bx +
bx *
0)
bx (
bx '
bx &
0%
bx $
bz #
bz "
bz !
$end
#1
b0 /
b0 -
b0 $
b0 ,
b0 .
b1000000000000000 1
1)
1%
#2
0)
0%
#3
1%
#4
b0 '
b0 +
b0 (
b0 &
b0 *
0%
#5
1%
#6
b10 '
b10 +
0%
#7
b10 /
b10000 2
1%
#8
0%
#9
b100 /
b10000 2
1%
#10
b1 4
0%
#11
b110 /
b10000 2
1%
#12
b10 4
0%
#13
b1000 /
b10000 2
1%
#14
b11 4
0%
#15
b1010 /
b10000 2
1%
#16
b100 4
0%
#17
b1100 /
b10000 2
1%
#18
b101 4
0%
#19
b1110 /
b10000 2
1%
#20
b110 4
0%
#21
b0 /
b10000 2
1%
#22
b111 4
0%
#23
b10 /
b10000 2
1%
#24
b0 '
b0 +
b1 &
b1 *
b1000 4
0%
#25
b0 /
1%
#26
b10 '
b10 +
0%
#27
b10 /
b1 $
b1 ,
b1 .
b10000 2
1%
#28
b1 (
b0 4
0%
#29
b100 /
b0 $
b0 ,
b0 .
b10000 2
1%
#30
b1 4
0%
#31
b110 /
b10000 2
1%
#32
b10 4
0%
#33
b1000 /
b10000 2
1%
#34
b11 4
0%
#35
b1010 /
b10000 2
1%
#36
b100 4
0%
#37
b1100 /
b10000 2
1%
#38
b101 4
0%
#39
b1110 /
b10000 2
1%
#40
b110 4
0%
#41
b0 /
b10000 2
1%
#42
b111 4
0%
#43
b10 /
b1 $
b1 ,
b1 .
b10000 2
1%
#44
b0 '
b0 +
b0 (
b10 &
b10 *
b1000 4
0%
#45
b0 /
1%
#46
b10 '
b10 +
0%
#47
b10 /
b10 $
b10 ,
b10 .
b10000 2
1%
#48
b10 (
b0 4
0%
#49
b100 /
b0 $
b0 ,
b0 .
b10000 2
1%
#50
b1 4
0%
#51
b110 /
b10000 2
1%
#52
b10 4
0%
#53
b1000 /
b10000 2
1%
#54
b11 4
0%
#55
b1010 /
b10000 2
1%
#56
b100 4
0%
#57
b1100 /
b10000 2
1%
#58
b101 4
0%
#59
b1110 /
b10000 2
1%
#60
b110 4
0%
#61
b0 /
b10000 2
1%
#62
b111 4
0%
#63
b10 /
b10 $
b10 ,
b10 .
b10000 2
1%
#64
b0 '
b0 +
b0 (
b11 &
b11 *
b1000 4
0%
#65
b0 /
1%
#66
b10 '
b10 +
0%
#67
b10 /
b11 $
b11 ,
b11 .
b10000 2
1%
#68
b11 (
b0 4
0%
#69
b100 /
b0 $
b0 ,
b0 .
b10000 2
1%
#70
b1 4
0%
#71
b110 /
b10000 2
1%
#72
b10 4
0%
#73
b1000 /
b10000 2
1%
#74
b11 4
0%
#75
b1010 /
b10000 2
1%
#76
b100 4
0%
#77
b1100 /
b10000 2
1%
#78
b101 4
0%
#79
b1110 /
b10000 2
1%
#80
b110 4
0%
#81
b0 /
b10000 2
1%
#82
b111 4
0%
#83
b10 /
b11 $
b11 ,
b11 .
b10000 2
1%
#84
b0 '
b0 +
b0 (
b100 &
b100 *
b1000 4
0%
#85
b0 /
1%
#86
b10 '
b10 +
0%
#87
b10 /
b100 $
b100 ,
b100 .
b10000 2
1%
#88
b100 (
b0 4
0%
#89
b100 /
b0 $
b0 ,
b0 .
b10000 2
1%
#90
b1 4
0%
#91
b110 /
b10000 2
1%
#92
b10 4
0%
#93
b1000 /
b10000 2
1%
#94
b11 4
0%
#95
b1010 /
b10000 2
1%
#96
b100 4
0%
#97
b1100 /
b10000 2
1%
#98
b101 4
0%
#99
b1110 /
b10000 2
1%
#100
b110 4
0%
#101
b0 /
b10000 2
1%
#102
b111 4
0%
#103
b10 /
b100 $
b100 ,
b100 .
b10000 2
1%
#104
b0 '
b0 +
b0 (
b101 &
b101 *
b1000 4
0%
#105
b0 /
1%
#106
b10 '
b10 +
0%
#107
b10 /
b101 $
b101 ,
b101 .
b10000 2
1%
#108
b101 (
b0 4
0%
#109
b100 /
b0 $
b0 ,
b0 .
b10000 2
1%
#110
b1 4
0%
#111
b110 /
b10000 2
1%
#112
b10 4
0%
#113
b1000 /
b10000 2
1%
#114
b11 4
0%
#115
b1010 /
b10000 2
1%
#116
b100 4
0%
#117
b1100 /
b10000 2
1%
#118
b101 4
0%
#119
b1110 /
b10000 2
1%
#120
b110 4
0%
#121
b0 /
b10000 2
1%
#122
b111 4
0%
#123
b10 /
b101 $
b101 ,
b101 .
b10000 2
1%
#124
b0 '
b0 +
b0 (
b110 &
b110 *
b1000 4
0%
#125
b0 /
1%
#126
b10 '
b10 +
0%
#127
b10 /
b110 $
b110 ,
b110 .
b10000 2
1%
#128
b110 (
b0 4
0%
#129
b100 /
b0 $
b0 ,
b0 .
b10000 2
1%
#130
b1 4
0%
#131
b110 /
b10000 2
1%
#132
b10 4
0%
#133
b1000 /
b10000 2
1%
#134
b11 4
0%
#135
b1010 /
b10000 2
1%
#136
b100 4
0%
#137
b1100 /
b10000 2
1%
#138
b101 4
0%
#139
b1110 /
b10000 2
1%
#140
b110 4
0%
#141
b0 /
b10000 2
1%
#142
b111 4
0%
#143
b10 /
b110 $
b110 ,
b110 .
b10000 2
1%
#144
b0 '
b0 +
b0 (
b111 &
b111 *
b1000 4
0%
#145
b0 /
1%
#146
b10 '
b10 +
0%
#147
b10 /
b111 $
b111 ,
b111 .
b10000 2
1%
#148
b111 (
b0 4
0%
#149
b100 /
b0 $
b0 ,
b0 .
b10000 2
1%
#150
b1 4
0%
#151
b110 /
b10000 2
1%
#152
b10 4
0%
#153
b1000 /
b10000 2
1%
#154
b11 4
0%
#155
b1010 /
b10000 2
1%
#156
b100 4
0%
#157
b1100 /
b10000 2
1%
#158
b101 4
0%
#159
b1110 /
b10000 2
1%
#160
b110 4
0%
#161
b0 /
b10000 2
1%
#162
b111 4
0%
#163
b10 /
b111 $
b111 ,
b111 .
b10000 2
1%
#164
b0 '
b0 +
b0 (
b1000 &
b1000 *
b1000 4
0%
#165
b0 /
1%
#166
b10 '
b10 +
0%
#167
b10 /
b1000 $
b1000 ,
b1000 .
b10000 2
1%
#168
b1000 (
b0 4
0%
#169
b100 /
b0 $
b0 ,
b0 .
b10000 2
1%
#170
b1 4
0%
#171
b110 /
b10000 2
1%
#172
b10 4
0%
#173
b1000 /
b10000 2
1%
#174
b11 4
0%
#175
b1010 /
b10000 2
1%
#176
b100 4
0%
#177
b1100 /
b10000 2
1%
#178
b101 4
0%
#179
b1110 /
b10000 2
1%
#180
b110 4
0%
#181
b0 /
b10000 2
1%
#182
b111 4
0%
#183
b10 /
b1000 $
b1000 ,
b1000 .
b10000 2
1%
#184
b0 '
b0 +
b0 (
b1001 &
b1001 *
b1000 4
0%
#185
b0 /
1%
#186
b10 '
b10 +
0%
#187
b10 /
b1001 $
b1001 ,
b1001 .
b10000 2
1%
#188
b1001 (
b0 4
0%
#189
b100 /
b0 $
b0 ,
b0 .
b10000 2
1%
#190
b1 4
0%
#191
b110 /
b10000 2
1%
#192
b10 4
0%
#193
b1000 /
b10000 2
1%
#194
b11 4
0%
#195
b1010 /
b10000 2
1%
#196
b100 4
0%
#197
b1100 /
b10000 2
1%
#198
b101 4
0%
#199
b1110 /
b10000 2
1%
#200
b110 4
0%
#201
b0 /
b10000 2
1%
#202
b111 4
0%
#203
b10 /
b1001 $
b1001 ,
b1001 .
b10000 2
1%
#204
b0 '
b0 +
b0 (
b1010 &
b1010 *
b1000 4
0%
#205
b0 /
1%
#206
b10 '
b10 +
0%
#207
b10 /
b1010 $
b1010 ,
b1010 .
b10000 2
1%
#208
b1010 (
b0 4
0%
#209
b100 /
b0 $
b0 ,
b0 .
b10000 2
1%
#210
b1 4
0%
#211
b110 /
b10000 2
1%
#212
b10 4
0%
#213
b1000 /
b10000 2
1%
#214
b11 4
0%
#215
b1010 /
b10000 2
1%
#216
b100 4
0%
#217
b1100 /
b10000 2
1%
#218
b101 4
0%
#219
b1110 /
b10000 2
1%
#220
b110 4
0%
#221
b0 /
b10000 2
1%
#222
b111 4
0%
#223
b10 /
b1010 $
b1010 ,
b1010 .
b10000 2
1%
#224
b0 '
b0 +
b0 (
b1011 &
b1011 *
b1000 4
0%
#225
b0 /
1%
#226
b10 '
b10 +
0%
#227
b10 /
b1011 $
b1011 ,
b1011 .
b10000 2
1%
#228
b1011 (
b0 4
0%
#229
b100 /
b0 $
b0 ,
b0 .
b10000 2
1%
#230
b1 4
0%
#231
b110 /
b10000 2
1%
#232
b10 4
0%
#233
b1000 /
b10000 2
1%
#234
b11 4
0%
#235
b1010 /
b10000 2
1%
#236
b100 4
0%
#237
b1100 /
b10000 2
1%
#238
b101 4
0%
#239
b1110 /
b10000 2
1%
#240
b110 4
0%
#241
b0 /
b10000 2
1%
#242
b111 4
0%
#243
b10 /
b1011 $
b1011 ,
b1011 .
b10000 2
1%
#244
b0 '
b0 +
b0 (
b1100 &
b1100 *
b1000 4
0%
#245
b0 /
1%
#246
b10 '
b10 +
0%
#247
b10 /
b1100 $
b1100 ,
b1100 .
b10000 2
1%
#248
b1100 (
b0 4
0%
#249
b100 /
b0 $
b0 ,
b0 .
b10000 2
1%
#250
b1 4
0%
#251
b110 /
b10000 2
1%
#252
b10 4
0%
#253
b1000 /
b10000 2
1%
#254
b11 4
0%
#255
b1010 /
b10000 2
1%
#256
b100 4
0%
#257
b1100 /
b10000 2
1%
#258
b101 4
0%
#259
b1110 /
b10000 2
1%
#260
b110 4
0%
#261
b0 /
b10000 2
1%
#262
b111 4
0%
#263
b10 /
b1100 $
b1100 ,
b1100 .
b10000 2
1%
#264
b0 '
b0 +
b0 (
b1101 &
b1101 *
b1000 4
0%
#265
b0 /
1%
#266
b10 '
b10 +
0%
#267
b10 /
b1101 $
b1101 ,
b1101 .
b10000 2
1%
#268
b1101 (
b0 4
0%
#269
b100 /
b0 $
b0 ,
b0 .
b10000 2
1%
#270
b1 4
0%
#271
b110 /
b10000 2
1%
#272
b10 4
0%
#273
b1000 /
b10000 2
1%
#274
b11 4
0%
#275
b1010 /
b10000 2
1%
#276
b100 4
0%
#277
b1100 /
b10000 2
1%
#278
b101 4
0%
#279
b1110 /
b10000 2
1%
#280
b110 4
0%
#281
b0 /
b10000 2
1%
#282
b111 4
0%
#283
b10 /
b1101 $
b1101 ,
b1101 .
b10000 2
1%
#284
b0 '
b0 +
b0 (
b1110 &
b1110 *
b1000 4
0%
#285
b0 /
1%
#286
b10 '
b10 +
0%
#287
b10 /
b1110 $
b1110 ,
b1110 .
b10000 2
1%
#288
b1110 (
b0 4
0%
#289
b100 /
b0 $
b0 ,
b0 .
b10000 2
1%
#290
b1 4
0%
#291
b110 /
b10000 2
1%
#292
b10 4
0%
#293
b1000 /
b10000 2
1%
#294
b11 4
0%
#295
b1010 /
b10000 2
1%
#296
b100 4
0%
#297
b1100 /
b10000 2
1%
#298
b101 4
0%
#299
b1110 /
b10000 2
1%
#300
b110 4
0%
#301
b0 /
b10000 2
1%
#302
b111 4
0%
#303
b10 /
b1110 $
b1110 ,
b1110 .
b10000 2
1%
#304
b0 '
b0 +
b0 (
b1111 &
b1111 *
b1000 4
0%
#305
b0 /
1%
#306
b10 '
b10 +
0%
#307
b10 /
b1111 $
b1111 ,
b1111 .
b10000 2
1%
#308
b1111 (
b0 4
0%
#309
b100 /
b0 $
b0 ,
b0 .
b10000 2
1%
#310
b1 4
0%
#311
b110 /
b10000 2
1%
#312
b10 4
0%
#313
b1000 /
b10000 2
1%
#314
b11 4
0%
#315
b1010 /
b10000 2
1%
#316
b100 4
0%
#317
b1100 /
b10000 2
1%
#318
b101 4
0%
#319
b1110 /
b10000 2
1%
#320
b110 4
0%
#321
b0 /
b10000 2
1%
#322
b111 4
0%
#323
b10 /
b1111 $
b1111 ,
b1111 .
b10000 2
1%
#324
b0 '
b0 +
b0 (
b10000 &
b10000 *
b1000 4
0%
#325
b0 /
1%
#326
b10 '
b10 +
0%
#327
b10 /
b10000 $
b10000 ,
b10000 .
b10000 2
1%
#328
b10000 (
b0 4
0%
#329
b100 /
b0 $
b0 ,
b0 .
b10000 2
1%
#330
b1 4
0%
#331
b110 /
b10000 2
1%
#332
b10 4
0%
#333
b1000 /
b10000 2
1%
#334
b11 4
0%
#335
b1010 /
b10000 2
1%
#336
b100 4
0%
#337
b1100 /
b10000 2
1%
#338
b101 4
0%
#339
b1110 /
b10000 2
1%
#340
b110 4
0%
#341
b0 /
b10000 2
1%
#342
b111 4
0%
#343
b10 /
b10000 $
b10000 ,
b10000 .
b10000 2
1%
#344
b0 '
b0 +
b0 (
b10001 &
b10001 *
b1000 4
0%
#345
b0 /
1%
#346
b10 '
b10 +
0%
#347
b10 /
b10001 $
b10001 ,
b10001 .
b10000 2
1%
#348
b10001 (
b0 4
0%
#349
b100 /
b0 $
b0 ,
b0 .
b10000 2
1%
#350
b1 4
0%
#351
b110 /
b10000 2
1%
#352
b10 4
0%
#353
b1000 /
b10000 2
1%
#354
b11 4
0%
#355
b1010 /
b10000 2
1%
#356
b100 4
0%
#357
b1100 /
b10000 2
1%
#358
b101 4
0%
#359
b1110 /
b10000 2
1%
#360
b110 4
0%
#361
b0 /
b10000 2
1%
#362
b111 4
0%
#363
b10 /
b10001 $
b10001 ,
b10001 .
b10000 2
1%
#364
b0 '
b0 +
b0 (
b10010 &
b10010 *
b1000 4
0%
#365
b0 /
1%
#366
b10 '
b10 +
0%
#367
b10 /
b10010 $
b10010 ,
b10010 .
b10000 2
1%
#368
b10010 (
b0 4
0%
#369
b100 /
b0 $
b0 ,
b0 .
b10000 2
1%
#370
b1 4
0%
#371
b110 /
b10000 2
1%
#372
b10 4
0%
#373
b1000 /
b10000 2
1%
#374
b11 4
0%
#375
b1010 /
b10000 2
1%
#376
b100 4
0%
#377
b1100 /
b10000 2
1%
#378
b101 4
0%
#379
b1110 /
b10000 2
1%
#380
b110 4
0%
#381
b0 /
b10000 2
1%
#382
b111 4
0%
#383
b10 /
b10010 $
b10010 ,
b10010 .
b10000 2
1%
#384
b0 '
b0 +
b0 (
b10011 &
b10011 *
b1000 4
0%
#385
b0 /
1%
#386
b10 '
b10 +
0%
#387
b10 /
b10011 $
b10011 ,
b10011 .
b10000 2
1%
#388
b10011 (
b0 4
0%
#389
b100 /
b0 $
b0 ,
b0 .
b10000 2
1%
#390
b1 4
0%
#391
b110 /
b10000 2
1%
#392
b10 4
0%
#393
b1000 /
b10000 2
1%
#394
b11 4
0%
#395
b1010 /
b10000 2
1%
#396
b100 4
0%
#397
b1100 /
b10000 2
1%
#398
b101 4
0%
#399
b1110 /
b10000 2
1%
#400
b110 4
0%
#401
b0 /
b10000 2
1%
#402
b111 4
0%
#403
b10 /
b10011 $
b10011 ,
b10011 .
b10000 2
1%
#404
b0 '
b0 +
b0 (
b10100 &
b10100 *
b1000 4
0%
#405
b0 /
1%
#406
b10 '
b10 +
0%
#407
b10 /
b10100 $
b10100 ,
b10100 .
b10000 2
1%
#408
b10100 (
b0 4
0%
#409
b100 /
b0 $
b0 ,
b0 .
b10000 2
1%
#410
b1 4
0%
#411
b110 /
b10000 2
1%
#412
b10 4
0%
#413
b1000 /
b10000 2
1%
#414
b11 4
0%
#415
b1010 /
b10000 2
1%
#416
b100 4
0%
#417
b1100 /
b10000 2
1%
#418
b101 4
0%
#419
b1110 /
b10000 2
1%
#420
b110 4
0%
#421
b0 /
b10000 2
1%
#422
b111 4
0%
#423
b10 /
b10100 $
b10100 ,
b10100 .
b10000 2
1%
#424
b0 '
b0 +
b0 (
b10101 &
b10101 *
b1000 4
0%
#425
b0 /
1%
#426
b10 '
b10 +
0%
#427
b10 /
b10101 $
b10101 ,
b10101 .
b10000 2
1%
#428
b10101 (
b0 4
0%
#429
b100 /
b0 $
b0 ,
b0 .
b10000 2
1%
#430
b1 4
0%
#431
b110 /
b10000 2
1%
#432
b10 4
0%
#433
b1000 /
b10000 2
1%
#434
b11 4
0%
#435
b1010 /
b10000 2
1%
#436
b100 4
0%
#437
b1100 /
b10000 2
1%
#438
b101 4
0%
#439
b1110 /
b10000 2
1%
#440
b110 4
0%
#441
b0 /
b10000 2
1%
#442
b111 4
0%
#443
b10 /
b10101 $
b10101 ,
b10101 .
b10000 2
1%
#444
b0 '
b0 +
b0 (
b10110 &
b10110 *
b1000 4
0%
#445
b0 /
1%
#446
b10 '
b10 +
0%
#447
b10 /
b10110 $
b10110 ,
b10110 .
b10000 2
1%
#448
b10110 (
b0 4
0%
#449
b100 /
b0 $
b0 ,
b0 .
b10000 2
1%
#450
b1 4
0%
#451
b110 /
b10000 2
1%
#452
b10 4
0%
#453
b1000 /
b10000 2
1%
#454
b11 4
0%
#455
b1010 /
b10000 2
1%
#456
b100 4
0%
#457
b1100 /
b10000 2
1%
#458
b101 4
0%
#459
b1110 /
b10000 2
1%
#460
b110 4
0%
#461
b0 /
b10000 2
1%
#462
b111 4
0%
#463
b10 /
b10110 $
b10110 ,
b10110 .
b10000 2
1%
#464
b0 '
b0 +
b0 (
b10111 &
b10111 *
b1000 4
0%
#465
b0 /
1%
#466
b10 '
b10 +
0%
#467
b10 /
b10111 $
b10111 ,
b10111 .
b10000 2
1%
#468
b10111 (
b0 4
0%
#469
b100 /
b0 $
b0 ,
b0 .
b10000 2
1%
#470
b1 4
0%
#471
b110 /
b10000 2
1%
#472
b10 4
0%
#473
b1000 /
b10000 2
1%
#474
b11 4
0%
#475
b1010 /
b10000 2
1%
#476
b100 4
0%
#477
b1100 /
b10000 2
1%
#478
b101 4
0%
#479
b1110 /
b10000 2
1%
#480
b110 4
0%
#481
b0 /
b10000 2
1%
#482
b111 4
0%
#483
b10 /
b10111 $
b10111 ,
b10111 .
b10000 2
1%
#484
b0 '
b0 +
b0 (
b11000 &
b11000 *
b1000 4
0%
#485
b0 /
1%
#486
b10 '
b10 +
0%
#487
b10 /
b11000 $
b11000 ,
b11000 .
b10000 2
1%
#488
b11000 (
b0 4
0%
#489
b100 /
b0 $
b0 ,
b0 .
b10000 2
1%
#490
b1 4
0%
#491
b110 /
b10000 2
1%
#492
b10 4
0%
#493
b1000 /
b10000 2
1%
#494
b11 4
0%
#495
b1010 /
b10000 2
1%
#496
b100 4
0%
#497
b1100 /
b10000 2
1%
#498
b101 4
0%
#499
b1110 /
b10000 2
1%
#500
b110 4
0%
#501
b0 /
b10000 2
1%
#502
b111 4
0%
#503
b10 /
b11000 $
b11000 ,
b11000 .
b10000 2
1%
#504
b0 '
b0 +
b0 (
b11001 &
b11001 *
b1000 4
0%
#505
b0 /
1%
#506
b10 '
b10 +
0%
#507
b10 /
b11001 $
b11001 ,
b11001 .
b10000 2
1%
#508
b11001 (
b0 4
0%
#509
b100 /
b0 $
b0 ,
b0 .
b10000 2
1%
#510
b1 4
0%
#511
b110 /
b10000 2
1%
#512
b10 4
0%
#513
b1000 /
b10000 2
1%
#514
b11 4
0%
#515
b1010 /
b10000 2
1%
#516
b100 4
0%
#517
b1100 /
b10000 2
1%
#518
b101 4
0%
#519
b1110 /
b10000 2
1%
#520
b110 4
0%
#521
b0 /
b10000 2
1%
#522
b111 4
0%
