2-Lab/mem.sv
module mem #(
    parameter MEM_ADDR_SIZE = 10 + 9, 
    parameter BUS_SIZE = 16 ,
    parameter CACHE_OFFSET_SIZE = 4,
    parameter CACHE_LINE_SIZE = 16
    ) (
    input clk,
    input reset,
    input [MEM_ADDR_SIZE-CACHE_OFFSET_SIZE-1:0] address,
    inout [BUS_SIZE-1:0] data,
    input [2-1:0] command
);

    // 512KB = 2^9 * 2^10 = 2^19 = 2^15 lines * 2^4 bits in each line (16 8-bit words)
    parameter MEM_SIZE = 1 << (MEM_ADDR_SIZE-CACHE_OFFSET_SIZE); // 2^15 cache lines

    localparam  C2_NOP      = 3'd0,
                C2_RESPONSE = 3'd1,
                C2_READ     = 3'd2,
                C2_WRITE    = 3'd3;

    reg [CACHE_LINE_SIZE*8-1:0] storage [MEM_SIZE-1:0]; // 2^15 16-byte lines
    reg [BUS_SIZE-1:0] data_buff; // single bus
    reg [2-1:0] command_buff;

    reg [CACHE_OFFSET_SIZE-1:0] rwPosition; // ptr to next 2 bytes to read/write

    integer SEED = 225526;



    always @(posedge clk or posedge reset) begin
        if (reset) begin
            for (int i = 0; i < 99; i=i+1) begin
                storage[i] = $random(SEED)>>16;
            end
            $display("filled");

            data_buff = 'z;
            command_buff = 0;
            rwPosition = 0;
        end else begin
            command_buff = 0;
            if (command == C2_READ) begin
                // READ
                for (int i=0; i<CACHE_LINE_SIZE; i=i+1) begin
                    data_buff[i] = storage[address][rwPosition*8 + i];
                end
                rwPosition += 2;
            end else if (command == C2_WRITE) begin
                // WRITE
                // $display("before: %b", storage[address]);
                for (int i=0; i<CACHE_LINE_SIZE; i=i+1) begin
                    storage[address][rwPosition*8 + i] = data[i];
                end
                // $display("after : %b", storage[address]);
                rwPosition += 2;
            end else begin
                rwPosition = 0;
                data_buff = 'z;
            end
        end
    end

    assign data = data_buff;

endmodule

2-Lab/cache.sv
module cache#(
    parameter BUS_SIZE = 16 ,
    parameter MEM_ADDR_SIZE = 10 + 9,   // log2(MEM_SIZE)
    parameter CACHE_OFFSET_SIZE = 4,    // log2(CACHE_LINE_SIZE)
    parameter CACHE_LINE_SIZE   = 16
    ) (
    input clk,
    input reset,
    input [MEM_ADDR_SIZE-CACHE_OFFSET_SIZE-1:0] cpu_address,
    inout [BUS_SIZE-1:0] cpu_data,
    inout [3-1:0] cpu_command,

    output [MEM_ADDR_SIZE-CACHE_OFFSET_SIZE-1:0] mem_address,
    inout [BUS_SIZE-1:0] mem_data,
    inout [2-1:0] mem_command
);

    parameter CACHE_WAY         = 2;

    parameter CACHE_LINE_COUNT  = 64;
    parameter CACHE_SETS_COUNT  = CACHE_LINE_COUNT/CACHE_WAY; 
    parameter CACHE_SIZE        = CACHE_LINE_COUNT * CACHE_LINE_SIZE;
   
    parameter CACHE_SET_SIZE    = 5;    // log2(CACHE_SETS_COUNT)
    parameter CACHE_TAG_SIZE    = 10;   // CACHE_LINE_SIZE - CACHE_SET_SIZE - CACHE_OFFSET_SIZE
    localparam  C1_NOP          = 3'd0,
                C1_READ8        = 3'd1,
                C1_READ16       = 3'd2,
                C1_READ32       = 3'd3,
                C1_INV_LINE     = 3'd4,
                C1_WRITE8       = 3'd5,
                C1_WRITE16      = 3'd6,
                C1_WRITE32_RESP = 3'd7;

    localparam  C2_NOP          = 2'd0,
                C2_RESPONSE     = 2'd1,
                C2_READ         = 2'd2,
                C2_WRITE        = 2'd3;

    // localparam  IDLE        = 3'd0,
    //             READ        = 3'd1,
    //             WRITE       = 3'd2,
    //             READMM      = 3'd3,
    //             WAITFORMM   = 3'd4,
    //             UPDATEMM    = 3'd5,
    //             UPDATECACHE = 3'd6;

    // reg [3-1:0] state;

    // STORAGE
    reg valid_array [CACHE_SETS_COUNT-1:0][CACHE_WAY-1:0];
    reg dirty_array [CACHE_SETS_COUNT-1:0][CACHE_WAY-1:0];
    reg last_used_array [CACHE_SETS_COUNT-1:0]; // lRU
    reg [CACHE_TAG_SIZE-1:0] tag_array [CACHE_SETS_COUNT-1:0][CACHE_WAY-1:0];
    reg [CACHE_LINE_SIZE*8-1:0] data_array [CACHE_SETS_COUNT-1:0][CACHE_WAY-1:0]; // stores lines

    reg [MEM_ADDR_SIZE-1:0] cpu_address_buff;
    reg [CACHE_TAG_SIZE-1:0] cpu_tag_buff;
    reg [CACHE_SET_SIZE-1:0] cpu_set_buff;
    reg [CACHE_OFFSET_SIZE-1:0] cpu_offset_buff;
    reg [BUS_SIZE-1:0] cpu_data_bus_buff; // single bus
    reg [3-1:0] cpu_command_buff;
    
    reg [MEM_ADDR_SIZE-CACHE_OFFSET_SIZE-1:0] mem_address_buff;
    reg [CACHE_LINE_SIZE*8-1:0] mem_line_buff; // single line
    reg [BUS_SIZE-1:0] mem_data_buff;
    reg [2-1:0] mem_command_buff;

    task delay;
        begin
            @(negedge clk);
        end
    endtask	

    task write_to_MM;
        $display("need_to_write_to_MM");
        $display("mem addr to write: %b", mem_address_buff);
        $display("write : %b", data_array[cpu_set_buff][last_used_array[cpu_set_buff]]);
        // set
        mem_command_buff = C2_WRITE;
        delay;
        // write
        for (int i=0; i<CACHE_LINE_SIZE/2; i=i+1) begin
            mem_data_buff = data_array[cpu_set_buff][last_used_array[cpu_set_buff]][BUS_SIZE*i +: BUS_SIZE];
            delay;
        end
        // restore
        mem_command_buff = C2_NOP;
        mem_data_buff = 'z;
    endtask

    reg index_in_set;
    task store;
        data_array[cpu_set_buff][index_in_set] = mem_line_buff;
        tag_array[cpu_set_buff][index_in_set] = cpu_tag_buff;
        valid_array[cpu_set_buff][index_in_set] = 1;
        dirty_array[cpu_set_buff][index_in_set] = 0;
        last_used_array[cpu_set_buff] = ~index_in_set; // opposite 
    endtask

    task read_cpu_address;
        mem_address_buff = cpu_address;
        cpu_tag_buff = cpu_address[CACHE_TAG_SIZE+CACHE_SET_SIZE-1:CACHE_SET_SIZE];
        cpu_set_buff = cpu_address[CACHE_SET_SIZE-1:0];

        while (mem_address_buff == cpu_address) begin 
            delay;
        end
        cpu_offset_buff = cpu_address[3:0];
    endtask

    reg [3-1:0] cur_cpu_command;
    task read_from_storage;
        case (cur_cpu_command)
            C1_READ8 : begin
                cpu_data_bus_buff = data_array[cpu_set_buff][index_in_set][cpu_offset_buff*8 +: 8];
            end
            C1_READ16 : begin
                cpu_data_bus_buff = data_array[cpu_set_buff][index_in_set][cpu_offset_buff*8 +: 16];
            end
            C1_READ32 : begin
                $display("C1_READ32!!!");
            end
        endcase
    endtask 

    task write_to_storage;
        case (cur_cpu_command)
            C1_WRITE8 : begin
                data_array[cpu_set_buff][index_in_set][cpu_offset_buff*8 +: 8] = cpu_data;
                dirty_array[cpu_set_buff][index_in_set] = 1;
            end
            C1_WRITE16 : begin
                data_array[cpu_set_buff][index_in_set][cpu_offset_buff*8 +: 16] = cpu_data;
                dirty_array[cpu_set_buff][index_in_set] = 1;
            end
        endcase    endtask

    initial begin
        mem_line_buff     =  0;
        cpu_data_bus_buff = 'z;
        cpu_command_buff  = 'z;
        cur_cpu_command   =  0;
        mem_command_buff  = 'z;
        mem_data_buff     = 'z;
    end

    always @(posedge clk or posedge reset) begin
        if (reset) begin
            for (int i=0; i<CACHE_SETS_COUNT; i=i+1) begin
                valid_array[i][0] =  0;
                dirty_array[i][0] =  0;
                tag_array[i][0]   = 'z;
                data_array[i][0]  = 'z;
                valid_array[i][1] =  0;
                dirty_array[i][1] =  0;
                tag_array[i][1]   = 'z;
                data_array[i][1]  = 'z;
            end
        end 
        if (cpu_command == C1_READ8 || cpu_command == C1_READ16 || cpu_command == C1_READ32) begin
            $display("C1_READX");
            cur_cpu_command = cpu_command;
            read_cpu_address;

            if (tag_array[cpu_set_buff][0] == cpu_tag_buff) begin
                if (valid_array[cpu_set_buff][0] == 1) begin
                    $display("found 0");
                    index_in_set = 0;
                    read_from_storage;
                end
            end else if (tag_array[cpu_set_buff][1] == cpu_tag_buff) begin
                if (valid_array[cpu_set_buff][1] == 1) begin
                    $display("found 1");
                    index_in_set = 1;
                    read_from_storage;
                end
            end else begin 
                $display("GO TO MM");
                // set
                mem_command_buff = C2_READ;
                delay;

                // read
                for (int i=0; i<CACHE_LINE_SIZE/2; i=i+1) begin
                    mem_line_buff[BUS_SIZE*i +: BUS_SIZE] = mem_data;
                    delay;
                end
                // $display("new data: %b", mem_line_buff);
                // $display("mem addr: %b", mem_address_buff);

                // restore
                mem_command_buff = C2_NOP;
                
                // try to write in cache storage
                if (valid_array[cpu_set_buff][0] == 0) begin
                    index_in_set = 0;
                    $display("store 0");
                    store;
                end else if (valid_array[cpu_set_buff][1] == 0) begin
                    index_in_set = 1;
                    $display("store 1");
                    store;
                end else begin
                    // LRU
                    if (dirty_array[cpu_set_buff][last_used_array[cpu_set_buff]] == 1) begin
                        $display("write to mm");
                        mem_address_buff[CACHE_TAG_SIZE+CACHE_SET_SIZE-1:CACHE_SET_SIZE] = tag_array[cpu_set_buff][last_used_array[cpu_set_buff]];
                        mem_address_buff[CACHE_SET_SIZE-1:0] = cpu_set_buff;
                        write_to_MM;
                    end
                    
                    index_in_set = last_used_array[cpu_set_buff];
                    store;
                end
                read_from_storage;
            end

            cpu_command_buff = C1_WRITE32_RESP;
            delay;
            cpu_command_buff = 'z;
            cpu_data_bus_buff = 'z;
            cur_cpu_command = 'z;

        end else if (cpu_command == C1_WRITE8 || cpu_command == C1_WRITE16) begin
            $display("C1_WRITEX");
            cur_cpu_command = cpu_command;
            read_cpu_address;

            if (tag_array[cpu_set_buff][0] == cpu_tag_buff) begin
                if (valid_array[cpu_set_buff][0] == 1) begin
                    $display("found 0");
                    index_in_set = 0;
                    write_to_storage;
                end
            end else if (tag_array[cpu_set_buff][1] == cpu_tag_buff) begin
                if (valid_array[cpu_set_buff][1] == 1) begin
                    $display("found 1");
                    index_in_set = 1;
                    write_to_storage;
                end
            end
            cpu_command_buff = C1_WRITE32_RESP;
            delay;
            cpu_command_buff = 'z;
            cur_cpu_command = 'z;
        end
    end

    assign mem_address = mem_address_buff;
    assign mem_data = mem_data_buff;
    assign mem_command = mem_command_buff;
    assign cpu_data = cpu_data_bus_buff;
    assign cpu_command = cpu_command_buff;

endmodule

2-Lab/cpu.sv
module cpu #(
    parameter MEM_ADDR_SIZE = 10 + 9, 
    parameter BUS_SIZE = 16,
    parameter CACHE_OFFSET_SIZE = 4
    ) (

    input clk,
    output [MEM_ADDR_SIZE-CACHE_OFFSET_SIZE-1:0] address,
    inout [BUS_SIZE-1:0] data,
    inout [3-1:0] command
);

    localparam  C1_NOP          = 3'd0,
                C1_READ8        = 3'd1,
                C1_READ16       = 3'd2,
                C1_READ32       = 3'd3,
                C1_INV_LINE     = 3'd4,
                C1_WRITE8       = 3'd5,
                C1_WRITE16      = 3'd6,
                C1_WRITE32_RESP = 3'd7;
    
    reg [MEM_ADDR_SIZE-1:0] cpu_address_buff;
    reg [MEM_ADDR_SIZE-CACHE_OFFSET_SIZE-1:0] address_bus_buff;
    reg [BUS_SIZE-1:0] data_to_write;
    reg [3-1:0] cpu_command_buff;
    reg [BUS_SIZE-1:0] recieved_data;


    task delay;
        begin
            @(negedge clk);
        end
    endtask	
    
    task send_address;
        address_bus_buff = cpu_address_buff[MEM_ADDR_SIZE-1:CACHE_OFFSET_SIZE];
        delay;
        address_bus_buff = cpu_address_buff[CACHE_OFFSET_SIZE-1:0];
        delay;
    endtask

    task wait_for_resp;
        while (command !== C1_WRITE32_RESP) begin 
            delay;
        end
    endtask

    task READ8;
        cpu_command_buff = C1_READ8;
        READ;
    endtask
    task READ16;
        cpu_command_buff = C1_READ16;
        READ;
    endtask

    task READ;
        send_address;
        cpu_command_buff = 'z;
        wait_for_resp;
        recieved_data = data;
    endtask

    task WRITE8;
        cpu_command_buff = C1_WRITE8;
        WRITE;
    endtask
    task WRITE16;
        cpu_command_buff = C1_WRITE16;
        WRITE;
    endtask

    task WRITE;
        send_address;
        cpu_command_buff = 'z;
        wait_for_resp;
        data_to_write = 'z;
    endtask
    initial begin
        address_bus_buff = 'z;
        cpu_command_buff = 'z;
        recieved_data = 0;
        data_to_write = 'z;
    end

    // Place for test calls
    initial begin
        delay;

        cpu_address_buff = 19'b0000000000_00010_0000;
        READ8;
        $display("recieved: %b", recieved_data);

        cpu_address_buff = 19'b0000000000_00010_0000;
        data_to_write = 16'b0101010101010101;
        WRITE16;
        $display("writen");
        delay;
        cpu_address_buff = 19'b0000000000_00010_0000;
        READ16;
        $display("recieved: %b", recieved_data);
        
        // // READ2
        // cpu_command_buff = C1_READ16;
        // cpu_address_buff = 15'b0000000000_00010;
        // delay;
        // cpu_address_buff = 15'b0000;
        // delay;
        // cpu_command_buff = 'z;
        // delay;
        // while (command !== C1_WRITE32_RESP) begin 
        //     delay;
        // end
        // recieved_data = data;
        // $display("recieved: %b", recieved_data);

        // // WRITE2
        // cpu_command_buff = C1_WRITE16;
        // cpu_address_buff = 15'b0000000000_00010;
        // data_to_write = 16'b1010101010101010;
        // delay;
        // cpu_address_buff = 15'b0000;
        // delay;
        // cpu_command_buff = 'z;
        // delay;
        // while (command !== C1_WRITE32_RESP) begin 
        //     delay;
        // end
        // data_to_write = 'z;
        
        // // READ3
        // cpu_command_buff = C1_READ16;
        // cpu_address_buff = 15'b0000000000_00010;
        // delay;
        // cpu_address_buff = 15'b0000;
        // delay;
        // cpu_command_buff = 'z;
        // delay;
        // while (command !== C1_WRITE32_RESP) begin 
        //     delay;
        // end
        // recieved_data = data;
        // $display("recieved: %b", recieved_data);
        
        // READ3
        // cpu_command_buff = C1_READ32;
        // cpu_address_buff = 15'b0000000001_00010;
        // delay;
        // cpu_address_buff = 15'b0000;
        // delay;
        // cpu_command_buff = 'z;
        // delay;
        // while (command !== C1_WRITE32_RESP) begin 
        //     delay;
        // end
        // recieved_data = data;
        // $display("recieved: %b", recieved_data);

        // // READ4
        // cpu_command_buff = C1_READ8;
        // cpu_address_buff = 15'b0000000011_00010;
        // delay;
        // cpu_address_buff = 15'b0000;
        // delay;
        // cpu_command_buff = 'z;
        // delay;
        // while (command !== C1_WRITE32_RESP) begin 
        //     delay;
        // end
        // recieved_data = data;
        // $display("recieved: %b", recieved_data);

        $finish();
    end

    assign address = address_bus_buff;
    assign data = data_to_write;
    assign command = cpu_command_buff;
    
endmodule

2-Lab/testbench.sv
module testbench ();
    parameter BUS_SIZE = 16;
    parameter MEM_ADDR_SIZE = 10 + 9;   // log2(MEM_SIZE)
    parameter CACHE_OFFSET_SIZE = $clog2(CACHE_LINE_SIZE);
    parameter CACHE_LINE_SIZE = 16;
    wire [MEM_ADDR_SIZE-CACHE_OFFSET_SIZE-1:0] cpu_address;
    wire [BUS_SIZE-1:0] cpu_data;
    wire [3-1:0] cpu_command;
    wire [MEM_ADDR_SIZE-CACHE_OFFSET_SIZE-1:0] mem_address;
    wire [BUS_SIZE-1:0] mem_data;
    wire [2-1:0] mem_command;

    reg clk;
    reg reset;


    cpu #(MEM_ADDR_SIZE, BUS_SIZE, CACHE_OFFSET_SIZE) 
    cpu (clk, cpu_address, cpu_data, cpu_command);

    cache #(BUS_SIZE, MEM_ADDR_SIZE, CACHE_OFFSET_SIZE, CACHE_LINE_SIZE)
    cache (clk, reset, 
    cpu_address, cpu_data, cpu_command,
    mem_address, mem_data, mem_command);

    mem #(MEM_ADDR_SIZE, BUS_SIZE, CACHE_OFFSET_SIZE, CACHE_LINE_SIZE) 
    mem(clk, reset, mem_address, mem_data, mem_command);

     task delay;
        begin
            @(negedge clk);
        end
    endtask	

    initial begin
        reset = 0;
        #1 reset = 1;
        #1 reset = 0;
        clk = 1'd0;

        forever begin
            #1 clk = ~clk;
            // $display("addr: %b", mem_address);
            // $display("data: %b", mem_data);
            // $display("cache.: %b", cache.mem_data_buff);
            // $display("mem.: %b", mem.data_buff);
            // $display("command: %b", mem_command);
        end
    end

    initial begin
        $dumpfile("dump_cache.vcd"); 
        $dumpvars;
    end

endmodule

2-Lab/dump_cache.vcd
$date
	Wed Nov 30 17:48:23 2022
$end
$version
	Icarus Verilog
$end
$timescale
	1s
$end
$scope module testbench $end
$var wire 3 ! cpu_command [2:0] $end
$var wire 16 " cpu_data [15:0] $end
$var wire 16 # mem_data [15:0] $end
$var wire 2 $ mem_command [1:0] $end
$var wire 15 % mem_address [14:0] $end
$var wire 15 & cpu_address [14:0] $end
$var reg 1 ' clk $end
$var reg 1 ( reset $end
$scope module cache $end
$var wire 1 ' clk $end
$var wire 3 ) cpu_command [2:0] $end
$var wire 16 * cpu_data [15:0] $end
$var wire 15 + mem_address [14:0] $end
$var wire 2 , mem_command [1:0] $end
$var wire 16 - mem_data [15:0] $end
$var wire 1 ( reset $end
$var wire 15 . cpu_address [14:0] $end
$var reg 3 / cpu_command_buff [2:0] $end
$var reg 16 0 cpu_data_bus_buff [15:0] $end
$var reg 4 1 cpu_offset_buff [3:0] $end
$var reg 5 2 cpu_set_buff [4:0] $end
$var reg 10 3 cpu_tag_buff [9:0] $end
$var reg 3 4 cur_cpu_command [2:0] $end
$var reg 1 5 index_in_set $end
$var reg 15 6 mem_address_buff [14:0] $end
$var reg 2 7 mem_command_buff [1:0] $end
$var reg 16 8 mem_data_buff [15:0] $end
$var reg 128 9 mem_line_buff [127:0] $end
$scope begin $ivl_for_loop1 $end
$var integer 32 : i [31:0] $end
$upscope $end
$scope begin $ivl_for_loop2 $end
$var integer 32 ; i [31:0] $end
$upscope $end
$scope task delay $end
$upscope $end
$scope task read_cpu_address $end
$upscope $end
$scope task read_from_storage $end
$upscope $end
$scope task store $end
$upscope $end
$scope task write_to_MM $end
$scope begin $ivl_for_loop0 $end
$var integer 32 < i [31:0] $end
$upscope $end
$upscope $end
$scope task write_to_storage $end
$upscope $end
$upscope $end
$scope module cpu $end
$var wire 15 = address [14:0] $end
$var wire 1 ' clk $end
$var wire 3 > command [2:0] $end
$var wire 16 ? data [15:0] $end
$var reg 15 @ address_bus_buff [14:0] $end
$var reg 19 A cpu_address_buff [18:0] $end
$var reg 3 B cpu_command_buff [2:0] $end
$var reg 16 C data_to_write [15:0] $end
$var reg 16 D recieved_data [15:0] $end
$scope task READ $end
$upscope $end
$scope task READ16 $end
$upscope $end
$scope task READ8 $end
$upscope $end
$scope task WRITE $end
$upscope $end
$scope task WRITE16 $end
$upscope $end
$scope task WRITE8 $end
$upscope $end
$scope task delay $end
$upscope $end
$scope task send_address $end
$upscope $end
$scope task wait_for_resp $end
$upscope $end
$upscope $end
$scope module mem $end
$var wire 15 E address [14:0] $end
$var wire 1 ' clk $end
$var wire 2 F command [1:0] $end
$var wire 16 G data [15:0] $end
$var wire 1 ( reset $end
$var reg 2 H command_buff [1:0] $end
$var reg 16 I data_buff [15:0] $end
$var reg 4 J rwPosition [3:0] $end
$var integer 32 K SEED [31:0] $end
$scope begin $ivl_for_loop3 $end
$var integer 32 L i [31:0] $end
$upscope $end
$scope begin $ivl_for_loop4 $end
$var integer 32 M i [31:0] $end
$upscope $end
$scope begin $ivl_for_loop5 $end
$var integer 32 N i [31:0] $end
$upscope $end
$upscope $end
$upscope $end
$enddefinitions $end
#0
$dumpvars
b0 N
b0 M
b0 L
b110111000011110110 K
bx J
bx I
bx H
bx G
bz F
bx E
b0 D
bz C
bz B
bx A
bz @
bz ?
bz >
bz =
b0 <
b0 ;
b0 :
b0 9
bz 8
bz 7
bx 6
x5
b0 4
bx 3
bx 2
bx 1
bz 0
bz /
bz .
bx -
bz ,
bx +
bz *
bz )
0(
x'
bz &
bx %
bz $
bx #
bz "
bz !
$end
#1
b0 J
b0 H
bz #
bz -
bz G
bz I
b1100011 L
b110000110000011110001000101 K
b100000 :
1(
#2
b10 &
b10 .
b10 =
b10 @
b1 !
b1 )
b1 >
b1 B
b100000 A
0'
0(
#3
b10 2
b0 3
b10 %
b10 +
b10 E
b10 6
b1 4
1'
#4
b10 $
b10 ,
b10 F
b10 7
b0 1
b0 &
b0 .
b0 =
b0 @
0'
#5
b10 J
b10000 M
b1000000111100 #
b1000000111100 -
b1000000111100 G
b1000000111100 I
1'
#6
b1000000111100 9
bz !
bz )
bz >
bz B
0'
#7
b100 J
b0 #
b0 -
b0 G
b0 I
b10000 M
1'
#8
b1 ;
0'
#9
b110 J
b10000 M
1'
#10
b10 ;
0'
#11
b1000 J
b10000 M
1'
#12
b11 ;
0'
#13
b1010 J
b10000 M
1'
#14
b100 ;
0'
#15
b1100 J
b10000 M
1'
#16
b101 ;
0'
#17
b1110 J
b10000 M
1'
#18
b110 ;
0'
#19
b0 J
b10000 M
1'
#20
b111 ;
0'
#21
b10 J
b1000000111100 #
b1000000111100 -
b1000000111100 G
b1000000111100 I
b10000 M
1'
#22
b111 !
b111 )
b111 >
b111 /
b111100 "
b111100 *
b111100 ?
b111100 0
05
b0 $
b0 ,
b0 F
b0 7
b1000 ;
0'
#23
bz #
bz -
bz G
bz I
b0 J
1'
#24
bz 4
bz 0
bz /
b10 &
b10 .
b10 =
b10 @
b110 !
b110 )
b110 >
b110 B
b101010101010101 "
b101010101010101 *
b101010101010101 ?
b101010101010101 C
b111100 D
0'
#25
b110 4
1'
#26
b11x !
b11x )
b11x >
b111 /
b0 &
b0 .
b0 =
b0 @
0'
#27
1'
#28
bz 4
bz /
bz "
bz *
bz ?
bz C
bz !
bz )
bz >
bz B
0'
#29
1'
#30
b10 &
b10 .
b10 =
b10 @
b10 !
b10 )
b10 >
b10 B
0'
#31
b10 4
1'
#32
bx1x !
bx1x )
bx1x >
b111 /
b101010101010101 "
b101010101010101 *
b101010101010101 ?
b101010101010101 0
b0 &
b0 .
b0 =
b0 @
0'
#33
1'
#34
bz 4
bz "
bz *
bz ?
bz 0
bz /
b101010101010101 D
bz !
bz )
bz >
bz B
0'
