2-Lab/mem.sv
module mem #(
    parameter MEM_ADDR_SIZE = 10 + 9, 
    parameter BUS_SIZE = 16 ,
    parameter CACHE_OFFSET_SIZE = 4,
    parameter CACHE_LINE_SIZE = 16
    ) (
    input clk,
    input reset,
    input [MEM_ADDR_SIZE-CACHE_OFFSET_SIZE-1:0] address,
    inout [BUS_SIZE-1:0] data,
    inout [2-1:0] command
);

    // 512KB = 2^9 * 2^10 = 2^19 = 2^15 lines * 2^4 bits in each line (16 8-bit words)
    parameter MEM_SIZE = 1 << (MEM_ADDR_SIZE-CACHE_OFFSET_SIZE); // 2^15 cache lines
    parameter RESPONSE_TIME = 100;

    localparam  C2_NOP      = 3'd0,
                C2_RESPONSE = 3'd1,
                C2_READ     = 3'd2,
                C2_WRITE    = 3'd3;

    reg [CACHE_LINE_SIZE*8-1:0] storage [MEM_SIZE-1:0]; // 2^15 16-byte lines
    reg [BUS_SIZE-1:0] data_buff; // single bus
    reg [2-1:0] command_buff;

    integer SEED = 225526;

    task delay;
        begin
            @(negedge clk);
        end
    endtask	

    task wait_and_response;
        repeat(RESPONSE_TIME) begin
            delay;
        end
        command_buff = C2_RESPONSE;
    endtask

    always @(posedge clk or posedge reset) begin
        if (reset) begin
            for (int i = 0; i < 99; i=i+1) begin
                storage[i] = $random(SEED)>>16;
            end
            data_buff = 'z;
            command_buff = 'z;
        end else begin
            if (command == C2_READ) begin
                wait_and_response;

                // READ
                for (int i=0; i<CACHE_LINE_SIZE/2; i=i+1) begin
                    data_buff = storage[address][BUS_SIZE*i +: BUS_SIZE];
                    delay;
                end
                command_buff = 'z;
                delay;
            end else if (command == C2_WRITE) begin
                data_buff = 'z;
                wait_and_response;

                // WRITE
                for (int i=0; i<CACHE_LINE_SIZE/2; i=i+1) begin
                    storage[address][BUS_SIZE*i +: BUS_SIZE] = data;
                    delay;
                end
                command_buff = 'z;
            end else begin
                data_buff = 'z;
            end
        end
    end

    assign data = data_buff;
    assign command = command_buff;
endmodule

2-Lab/cache.sv
module cache#(
    parameter BUS_SIZE = 16 ,
    parameter MEM_ADDR_SIZE = 10 + 9,
    parameter CACHE_OFFSET_SIZE = 4,
    parameter CACHE_LINE_SIZE   = 16
    ) (
    input clk,
    input reset,
    input [MEM_ADDR_SIZE-CACHE_OFFSET_SIZE-1:0] cpu_address,
    inout [BUS_SIZE-1:0] cpu_data,
    inout [3-1:0] cpu_command,

    output [MEM_ADDR_SIZE-CACHE_OFFSET_SIZE-1:0] mem_address,
    inout [BUS_SIZE-1:0] mem_data,
    inout [2-1:0] mem_command
);

    parameter CACHE_WAY         = 2;
    parameter CACHE_LINE_COUNT  = 64;

    parameter CACHE_SET_SIZE    = $clog2(CACHE_SETS_COUNT);
    parameter CACHE_TAG_SIZE    = CACHE_LINE_SIZE - CACHE_SET_SIZE - CACHE_OFFSET_SIZE;
    parameter CACHE_SIZE        = CACHE_LINE_COUNT * CACHE_LINE_SIZE;
    parameter CACHE_SETS_COUNT  = CACHE_LINE_COUNT/CACHE_WAY; 

    localparam  C1_NOP          = 3'd0,
                C1_READ8        = 3'd1,
                C1_READ16       = 3'd2,
                C1_READ32       = 3'd3,
                C1_INV_LINE     = 3'd4,
                C1_WRITE8       = 3'd5,
                C1_WRITE16      = 3'd6,
                C1_WRITE32_RESP = 3'd7;
                
    localparam  C2_NOP          = 2'd0,
                C2_RESPONSE     = 2'd1,
                C2_READ         = 2'd2,
                C2_WRITE        = 2'd3;

    // STORAGE
    reg valid_array [CACHE_SETS_COUNT-1:0][CACHE_WAY-1:0];
    reg dirty_array [CACHE_SETS_COUNT-1:0][CACHE_WAY-1:0];
    reg last_used_array [CACHE_SETS_COUNT-1:0]; // lRU
    reg [CACHE_TAG_SIZE-1:0] tag_array [CACHE_SETS_COUNT-1:0][CACHE_WAY-1:0];
    reg [CACHE_LINE_SIZE*8-1:0] data_array [CACHE_SETS_COUNT-1:0][CACHE_WAY-1:0]; // stores lines

    reg [CACHE_TAG_SIZE-1:0] cpu_tag_buff;
    reg [CACHE_SET_SIZE-1:0] cpu_set_buff;
    reg [CACHE_OFFSET_SIZE-1:0] cpu_offset_buff;
    reg [BUS_SIZE-1:0] cpu_data_bus_buff; // single bus
    reg [BUS_SIZE*2-1:0] cpu_data_to_write;
    reg [3-1:0] cpu_command_buff;
    
    reg [MEM_ADDR_SIZE-CACHE_OFFSET_SIZE-1:0] mem_address_buff;
    reg [CACHE_LINE_SIZE*8-1:0] mem_line_buff; // single line
    reg [BUS_SIZE-1:0] mem_data_buff;
    reg [2-1:0] mem_command_buff;

    task delay;
        begin
            @(negedge clk);
        end
    endtask	

    task wait_for_resp;
        while (mem_command !== C2_RESPONSE) begin 
            delay;
        end
    endtask

    task evict_if_dirty;
        if (dirty_array[cpu_set_buff][index_in_set] == 1) begin
            mem_address_buff[CACHE_TAG_SIZE+CACHE_SET_SIZE-1:CACHE_SET_SIZE] = tag_array[cpu_set_buff][index_in_set];
            mem_address_buff[CACHE_SET_SIZE-1:0] = cpu_set_buff;
            write_to_MM;
        end
    endtask

    task replace_from_MM;
        // set
        mem_command_buff = C2_READ;
        delay;
        mem_command_buff = 'z;
        wait_for_resp;

        // read
        for (int i=0; i<CACHE_LINE_SIZE/2; i=i+1) begin
            mem_line_buff[BUS_SIZE*i +: BUS_SIZE] = mem_data;
            delay;
        end

        // restore
        mem_command_buff = C2_NOP;
        
        // try to write in cache storage
        if (valid_array[cpu_set_buff][0] == 0) begin
            index_in_set = 0;
            store;
        end else if (valid_array[cpu_set_buff][1] == 0) begin
            index_in_set = 1;
            store;
        end else begin // evict
            // LRU
            index_in_set = last_used_array[cpu_set_buff];
            evict_if_dirty;
        
            index_in_set = last_used_array[cpu_set_buff];
            store;
        end
    endtask 

    task write_to_MM;
        // set
        mem_command_buff = C2_WRITE;
        delay;
        mem_command_buff = 'z;
        mem_data_buff = data_array[cpu_set_buff][index_in_set][0 +: BUS_SIZE];
        wait_for_resp;

        // write
        for (int i=1; i<CACHE_LINE_SIZE/2; i=i+1) begin
            mem_data_buff = data_array[cpu_set_buff][index_in_set][BUS_SIZE*i +: BUS_SIZE];
            delay;
        end
        // restore
        mem_command_buff = C2_NOP;
        mem_data_buff = 'z;
    endtask

    reg index_in_set;
    task store;
        data_array[cpu_set_buff][index_in_set] = mem_line_buff;
        tag_array[cpu_set_buff][index_in_set] = cpu_tag_buff;
        dirty_array[cpu_set_buff][index_in_set] = 0;
        update_flags;
    endtask

    task update_flags;
        valid_array[cpu_set_buff][index_in_set] = 1;
        last_used_array[cpu_set_buff] = ~index_in_set; // opposite 
    endtask

    task read_cpu_address;
        mem_address_buff = cpu_address;
        cpu_tag_buff = cpu_address[CACHE_TAG_SIZE+CACHE_SET_SIZE-1:CACHE_SET_SIZE];
        cpu_set_buff = cpu_address[CACHE_SET_SIZE-1:0];

        delay;
        
        cpu_offset_buff = cpu_address[3:0];
    endtask

    reg [3-1:0] cur_cpu_command;
    task read_from_storage;
        if (cur_cpu_command == C1_READ8) begin
            cpu_data_bus_buff = data_array[cpu_set_buff][index_in_set][cpu_offset_buff*8 +: 8];
        end else if (cur_cpu_command == C1_READ16 || cur_cpu_command == C1_READ32) begin
            cpu_data_bus_buff = data_array[cpu_set_buff][index_in_set][cpu_offset_buff*8 +: 16];
        end
    endtask 

    task write_to_storage;
        if (cur_cpu_command == C1_WRITE8) begin
            data_array[cpu_set_buff][index_in_set][cpu_offset_buff*8 +: 8] = cpu_data_to_write;
        end else if (cur_cpu_command == C1_WRITE16) begin
            data_array[cpu_set_buff][index_in_set][cpu_offset_buff*8 +: 16] = cpu_data_to_write;
        end else if (cur_cpu_command == C1_WRITE32_RESP) begin
            data_array[cpu_set_buff][index_in_set][cpu_offset_buff*8 +: 32] = cpu_data_to_write;
        end
        dirty_array[cpu_set_buff][index_in_set] = 1;
        update_flags;
    endtask

    always @(posedge clk or posedge reset) begin
        if (reset) begin
            for (int i=0; i<CACHE_SETS_COUNT; i=i+1) begin
                valid_array[i][0] =  0;
                dirty_array[i][0] =  0;
                tag_array[i][0]   = 'z;
                data_array[i][0]  = 'z;
                valid_array[i][1] =  0;
                dirty_array[i][1] =  0;
                tag_array[i][1]   = 'z;
                data_array[i][1]  = 'z;
            end
            mem_line_buff     =  0;
            cpu_data_bus_buff = 'z;
            cpu_command_buff  = 'z;
            cur_cpu_command   =  0;
            mem_command_buff  = 'z;
            mem_data_buff     = 'z;
        end else if (cpu_command == C1_READ8 || cpu_command == C1_READ16 || cpu_command == C1_READ32) begin
            cur_cpu_command = cpu_command;
            read_cpu_address;

            if (valid_array[cpu_set_buff][0] == 1 && tag_array[cpu_set_buff][0] == cpu_tag_buff) begin
                index_in_set = 0;
                read_from_storage;
            end else if (valid_array[cpu_set_buff][1] == 1 && tag_array[cpu_set_buff][1] == cpu_tag_buff) begin
                index_in_set = 1;
                read_from_storage;
            end else begin
                replace_from_MM;
                read_from_storage;
            end

            cpu_command_buff = C1_WRITE32_RESP;
            delay;

            if (cur_cpu_command == C1_READ32) begin
                delay;
                cpu_offset_buff += 2;
                read_from_storage;
                delay;
            end

            cpu_command_buff = 'z;
            cpu_data_bus_buff = 'z;
            cur_cpu_command = 'z;

        end else if (cpu_command == C1_WRITE8 || cpu_command == C1_WRITE16 || cpu_command == C1_WRITE32_RESP) begin
            cur_cpu_command = cpu_command;
            cpu_data_to_write[0 +: BUS_SIZE] = cpu_data;

            read_cpu_address;

            if (cpu_command == C1_WRITE32_RESP) begin
                cpu_data_to_write[BUS_SIZE +: BUS_SIZE] = cpu_data;
            end

            if (valid_array[cpu_set_buff][0] == 1 && tag_array[cpu_set_buff][0] == cpu_tag_buff) begin
                index_in_set = 0;
                write_to_storage;
            end else if (valid_array[cpu_set_buff][1] == 1 && tag_array[cpu_set_buff][1] == cpu_tag_buff) begin
                index_in_set = 1;
                write_to_storage;
            end else begin
                replace_from_MM;
                write_to_storage;
            end

            cpu_command_buff = C1_WRITE32_RESP;
            delay;
            cpu_command_buff = 'z;
            cur_cpu_command  = 'z;

        end else if (cpu_command == C1_INV_LINE) begin
            read_cpu_address;
            if (tag_array[cpu_set_buff][0] == cpu_tag_buff) begin
                index_in_set = 0;
                evict_if_dirty;
                valid_array[cpu_set_buff][0] = 0;
            end else if (tag_array[cpu_set_buff][1] == cpu_tag_buff) begin
                index_in_set = 0;
                evict_if_dirty;
                valid_array[cpu_set_buff][1] = 0;
            end

            cpu_command_buff = C1_WRITE32_RESP;
            delay;
            cpu_command_buff = 'z;
            cur_cpu_command  = 'z;
        end
    end

    assign mem_address = mem_address_buff;
    assign mem_data = mem_data_buff;
    assign mem_command = mem_command_buff;
    assign cpu_data = cpu_data_bus_buff;
    assign cpu_command = cpu_command_buff;

endmodule

2-Lab/cpu.sv
module cpu #(
    parameter MEM_ADDR_SIZE = 10 + 9, 
    parameter BUS_SIZE = 16,
    parameter CACHE_OFFSET_SIZE = 4
    ) (

    input clk,
    output [MEM_ADDR_SIZE-CACHE_OFFSET_SIZE-1:0] address,
    inout [BUS_SIZE-1:0] data,
    inout [3-1:0] command
);

    localparam  C1_NOP          = 3'd0,
                C1_READ8        = 3'd1,
                C1_READ16       = 3'd2,
                C1_READ32       = 3'd3,
                C1_INV_LINE     = 3'd4,
                C1_WRITE8       = 3'd5,
                C1_WRITE16      = 3'd6,
                C1_WRITE32_RESP = 3'd7;
    
    reg [MEM_ADDR_SIZE-1:0] cpu_address_buff;
    reg [MEM_ADDR_SIZE-CACHE_OFFSET_SIZE-1:0] address_bus_buff;
    reg [BUS_SIZE*2-1:0] data_to_write; 
    reg [BUS_SIZE-1:0] data_buff;
    reg [3-1:0] cpu_command_buff;
    reg [BUS_SIZE-1:0] recieved_data;
    reg [BUS_SIZE*2-1:0] local_storage;

    task delay;
        begin
            @(negedge clk);
        end
    endtask	
    
    task send_address;
        address_bus_buff = cpu_address_buff[MEM_ADDR_SIZE-1:CACHE_OFFSET_SIZE];
        delay;
        address_bus_buff = cpu_address_buff[CACHE_OFFSET_SIZE-1:0];
        delay;
    endtask

    task wait_for_resp;
        while (command !== C1_WRITE32_RESP) begin 
            delay;
        end
    endtask

    task READ8;
        cpu_command_buff = C1_READ8;
        READ;
        local_storage = recieved_data;
    endtask
    task READ16;
        cpu_command_buff = C1_READ16;
        READ;
        local_storage = recieved_data;
    endtask
    task READ32;
        cpu_command_buff = C1_READ32;
        READ;
        local_storage[BUS_SIZE-1:0] = recieved_data;
        READ;
        local_storage[BUS_SIZE*2-1:BUS_SIZE] = recieved_data;
        
    endtask

    task READ;
        send_address;
        cpu_command_buff = 'z;
        wait_for_resp;
        recieved_data = data;
    endtask

    task WRITE8;
        cpu_command_buff = C1_WRITE8;
        WRITE;
    endtask
    task WRITE16;
        cpu_command_buff = C1_WRITE16;
        WRITE;
    endtask
    task WRITE32;
        cpu_command_buff = C1_WRITE32_RESP;

        data_buff = data_to_write[BUS_SIZE-1:0];
        address_bus_buff = cpu_address_buff[MEM_ADDR_SIZE-1:CACHE_OFFSET_SIZE];
        delay;

        data_buff = data_to_write[BUS_SIZE*2-1:BUS_SIZE];
        address_bus_buff = cpu_address_buff[CACHE_OFFSET_SIZE-1:0];
        delay;

        cpu_command_buff = 'z;
        wait_for_resp;
        data_buff = 'z;
    endtask

    task WRITE;
        data_buff = data_to_write;
        send_address;
        cpu_command_buff = 'z;
        wait_for_resp;
        data_buff = 'z;
    endtask

    initial begin
        address_bus_buff = 'z;
        cpu_command_buff = 'z;
        recieved_data = 0;
        data_buff = 'z;
    end

    // Place for test calls
    initial begin
        delay;
        $display("----------------");

        cpu_address_buff = 19'b0000000000_01010_0000;
        $display("read from %b", cpu_address_buff);
        READ32;
        $display("data      %b", local_storage);
        $display("----------------");

        cpu_address_buff = 19'b0000000000_01010_0000;
        data_to_write = 32'b0101_0101_0101_0101_0101_0101_0101_0101;
        $display("write to  %b", cpu_address_buff);
        $display("data      %b", data_to_write);
        WRITE32;
        $display("----------------");
       
        cpu_address_buff = 19'b0000000000_01010_0000;
        $display("read from %b", cpu_address_buff);
        READ32;
        $display("data      %b", local_storage);
        $display("----------------");

        cpu_address_buff = 19'b0000000000_01010_0000;
        data_to_write = 32'b1111_1111_1111_1111_0000_0000_0000_0000;
        $display("write to  %b", cpu_address_buff);
        $display("data      %b", data_to_write);
        WRITE32;
        $display("----------------");
        
        cpu_address_buff = 19'b0000000000_01010_0000;
        $display("read from %b", cpu_address_buff);
        READ32;
        $display("data      %b", local_storage);
        $display("----------------");

        $finish();
    end

    assign address = address_bus_buff;
    assign data = data_buff;
    assign command = cpu_command_buff;
    
endmodule

2-Lab/testbench.sv
module testbench ();
    parameter BUS_SIZE = 16;
    parameter MEM_ADDR_SIZE = 10 + 9;   // log2(MEM_SIZE)
    parameter CACHE_OFFSET_SIZE = $clog2(CACHE_LINE_SIZE);
    parameter CACHE_LINE_SIZE = 16;
    wire [MEM_ADDR_SIZE-CACHE_OFFSET_SIZE-1:0] cpu_address;
    wire [BUS_SIZE-1:0] cpu_data;
    wire [3-1:0] cpu_command;
    wire [MEM_ADDR_SIZE-CACHE_OFFSET_SIZE-1:0] mem_address;
    wire [BUS_SIZE-1:0] mem_data;
    wire [2-1:0] mem_command;

    reg clk;
    reg reset;


    cpu #(MEM_ADDR_SIZE, BUS_SIZE, CACHE_OFFSET_SIZE) 
    cpu (clk, cpu_address, cpu_data, cpu_command);

    cache #(BUS_SIZE, MEM_ADDR_SIZE, CACHE_OFFSET_SIZE, CACHE_LINE_SIZE)
    cache (clk, reset, 
    cpu_address, cpu_data, cpu_command,
    mem_address, mem_data, mem_command);

    mem #(MEM_ADDR_SIZE, BUS_SIZE, CACHE_OFFSET_SIZE, CACHE_LINE_SIZE) 
    mem(clk, reset, mem_address, mem_data, mem_command);

     task delay;
        begin
            @(negedge clk);
        end
    endtask	

    initial begin
        reset = 0;
        #1 reset = 1;
        #1 reset = 0;
        clk = 1'd0;

        forever begin
            #1 clk = ~clk;
            // $display("addr: %b", mem_address);
            // $display("data: %b", mem_data);
            // $display("cache.: %b", cache.mem_data_buff);
            // $display("mem.: %b", mem.data_buff);
            // $display("command: %b", mem_command);
        end
    end

    initial begin
        $dumpfile("dump_cache.vcd"); 
        $dumpvars;
    end

endmodule

2-Lab/dump_cache.vcd
$date
	Thu Dec 01 01:43:41 2022
$end
$version
	Icarus Verilog
$end
$timescale
	1s
$end
$scope module testbench $end
$var wire 3 ! cpu_command [2:0] $end
$var wire 16 " cpu_data [15:0] $end
$var wire 2 # mem_command [1:0] $end
$var wire 16 $ mem_data [15:0] $end
$var wire 15 % mem_address [14:0] $end
$var wire 15 & cpu_address [14:0] $end
$var reg 1 ' clk $end
$var reg 1 ( reset $end
$scope module cache $end
$var wire 1 ' clk $end
$var wire 3 ) cpu_command [2:0] $end
$var wire 16 * cpu_data [15:0] $end
$var wire 15 + mem_address [14:0] $end
$var wire 2 , mem_command [1:0] $end
$var wire 16 - mem_data [15:0] $end
$var wire 1 ( reset $end
$var wire 15 . cpu_address [14:0] $end
$var reg 3 / cpu_command_buff [2:0] $end
$var reg 16 0 cpu_data_bus_buff [15:0] $end
$var reg 32 1 cpu_data_to_write [31:0] $end
$var reg 4 2 cpu_offset_buff [3:0] $end
$var reg 5 3 cpu_set_buff [4:0] $end
$var reg 7 4 cpu_tag_buff [6:0] $end
$var reg 3 5 cur_cpu_command [2:0] $end
$var reg 1 6 index_in_set $end
$var reg 15 7 mem_address_buff [14:0] $end
$var reg 2 8 mem_command_buff [1:0] $end
$var reg 16 9 mem_data_buff [15:0] $end
$var reg 128 : mem_line_buff [127:0] $end
$scope begin $ivl_for_loop2 $end
$var integer 32 ; i [31:0] $end
$upscope $end
$scope task delay $end
$upscope $end
$scope task evict_if_dirty $end
$upscope $end
$scope task read_cpu_address $end
$upscope $end
$scope task read_from_storage $end
$upscope $end
$scope task replace_from_MM $end
$scope begin $ivl_for_loop0 $end
$var integer 32 < i [31:0] $end
$upscope $end
$upscope $end
$scope task store $end
$upscope $end
$scope task update_flags $end
$upscope $end
$scope task wait_for_resp $end
$upscope $end
$scope task write_to_MM $end
$scope begin $ivl_for_loop1 $end
$var integer 32 = i [31:0] $end
$upscope $end
$upscope $end
$scope task write_to_storage $end
$upscope $end
$upscope $end
$scope module cpu $end
$var wire 15 > address [14:0] $end
$var wire 1 ' clk $end
$var wire 3 ? command [2:0] $end
$var wire 16 @ data [15:0] $end
$var reg 15 A address_bus_buff [14:0] $end
$var reg 19 B cpu_address_buff [18:0] $end
$var reg 3 C cpu_command_buff [2:0] $end
$var reg 16 D data_buff [15:0] $end
$var reg 32 E data_to_write [31:0] $end
$var reg 32 F local_storage [31:0] $end
$var reg 16 G recieved_data [15:0] $end
$scope task INV $end
$upscope $end
$scope task READ $end
$upscope $end
$scope task READ16 $end
$upscope $end
$scope task READ32 $end
$upscope $end
$scope task READ8 $end
$upscope $end
$scope task WRITE $end
$upscope $end
$scope task WRITE16 $end
$upscope $end
$scope task WRITE32 $end
$upscope $end
$scope task WRITE8 $end
$upscope $end
$scope task delay $end
$upscope $end
$scope task eviction_test $end
$upscope $end
$scope task invalidate_test $end
$upscope $end
$scope task read_write_test $end
$upscope $end
$scope task send_address $end
$upscope $end
$scope task wait_for_resp $end
$upscope $end
$upscope $end
$scope module mem $end
$var wire 15 H address [14:0] $end
$var wire 1 ' clk $end
$var wire 2 I command [1:0] $end
$var wire 16 J data [15:0] $end
$var wire 1 ( reset $end
$var reg 2 K command_buff [1:0] $end
$var reg 16 L data_buff [15:0] $end
$var integer 32 M SEED [31:0] $end
$scope begin $ivl_for_loop3 $end
$var integer 32 N i [31:0] $end
$upscope $end
$scope begin $ivl_for_loop4 $end
$var integer 32 O i [31:0] $end
$upscope $end
$scope begin $ivl_for_loop5 $end
$var integer 32 P i [31:0] $end
$upscope $end
$scope task delay $end
$upscope $end
$scope task wait_and_response $end
$upscope $end
$upscope $end
$scope task delay $end
$upscope $end
$upscope $end
$enddefinitions $end
#0
$dumpvars
b0 P
b0 O
b0 N
b110111000011110110 M
bx L
bx K
bx J
bx I
bx H
b0 G
bx F
bx E
bz D
bz C
bx B
bz A
bx @
bx ?
bz >
b0 =
b0 <
b0 ;
bx :
bx 9
bx 8
bx 7
x6
bx 5
bx 4
bx 3
bx 2
bx 1
bx 0
bx /
bz .
bx -
bx ,
bx +
bx *
bx )
0(
x'
bz &
bx %
bx $
bx #
bx "
bx !
$end
#1
bz #
bz ,
bz I
bz K
bz $
bz -
bz J
bz L
b1100011 N
b110000110000011110001000101 M
bz 9
bz 8
b0 5
bz !
bz )
bz ?
bz /
bz "
bz *
bz @
bz 0
b0 :
b100000 ;
1(
#2
b1110 &
b1110 .
b1110 >
b1110 A
b1 !
b1 )
b1 ?
b1 C
b11100000 B
0'
0(
#3
b1110 3
b0 4
b1110 %
b1110 +
b1110 H
b1110 7
b1 5
1'
#4
b10 #
b10 ,
b10 I
b10 8
b0 2
b0 &
b0 .
b0 >
b0 A
0'
#5
1'
#6
bz #
bz ,
bz I
bz 8
bz !
bz )
bz ?
bz C
0'
#7
1'
#8
0'
#9
1'
#10
0'
#11
1'
#12
0'
#13
1'
#14
0'
#15
1'
#16
0'
#17
1'
#18
0'
#19
1'
#20
0'
#21
1'
#22
0'
#23
1'
#24
0'
#25
1'
#26
0'
#27
1'
#28
0'
#29
1'
#30
0'
#31
1'
#32
0'
#33
1'
#34
0'
#35
1'
#36
0'
#37
1'
#38
0'
#39
1'
#40
0'
#41
1'
#42
0'
#43
1'
#44
0'
#45
1'
#46
0'
#47
1'
#48
0'
#49
1'
#50
0'
#51
1'
#52
0'
#53
1'
#54
0'
#55
1'
#56
0'
#57
1'
#58
0'
#59
1'
#60
0'
#61
1'
#62
0'
#63
1'
#64
0'
#65
1'
#66
0'
#67
1'
#68
0'
#69
1'
#70
0'
#71
1'
#72
0'
#73
1'
#74
0'
#75
1'
#76
0'
#77
1'
#78
0'
#79
1'
#80
0'
#81
1'
#82
0'
#83
1'
#84
0'
#85
1'
#86
0'
#87
1'
#88
0'
#89
1'
#90
0'
#91
1'
#92
0'
#93
1'
#94
0'
#95
1'
#96
0'
#97
1'
#98
0'
#99
1'
#100
0'
#101
1'
#102
0'
#103
1'
#104
0'
#105
1'
#106
0'
#107
1'
#108
0'
#109
1'
#110
0'
#111
1'
#112
0'
#113
1'
#114
0'
#115
1'
#116
0'
#117
1'
#118
0'
#119
1'
#120
0'
#121
1'
#122
0'
#123
1'
#124
0'
#125
1'
#126
0'
#127
1'
#128
0'
#129
1'
#130
0'
#131
1'
#132
0'
#133
1'
#134
0'
#135
1'
#136
0'
#137
1'
#138
0'
#139
1'
#140
0'
#141
1'
#142
0'
#143
1'
#144
0'
#145
1'
#146
0'
#147
1'
#148
0'
#149
1'
#150
0'
#151
1'
#152
0'
#153
1'
#154
0'
#155
1'
#156
0'
#157
1'
#158
0'
#159
1'
#160
0'
#161
1'
#162
0'
#163
1'
#164
0'
#165
1'
#166
0'
#167
1'
#168
0'
#169
1'
#170
0'
#171
1'
#172
0'
#173
1'
#174
0'
#175
1'
#176
0'
#177
1'
#178
0'
#179
1'
#180
0'
#181
1'
#182
0'
#183
1'
#184
0'
#185
1'
#186
0'
#187
1'
#188
0'
#189
1'
#190
0'
#191
1'
#192
0'
#193
1'
#194
0'
#195
1'
#196
0'
#197
1'
#198
0'
#199
1'
#200
0'
#201
1'
#202
0'
#203
1'
#204
b1001110001110100 $
b1001110001110100 -
b1001110001110100 J
b1001110001110100 L
b1 #
b1 ,
b1 I
b1 K
0'
#205
1'
#206
b1111111111111111 $
b1111111111111111 -
b1111111111111111 J
b1111111111111111 L
b1 O
b1001110001110100 :
0'
#207
1'
#208
b10 O
b11111111111111111001110001110100 :
b1 <
0'
#209
1'
#210
b11 O
b111111111111111111111111111111111001110001110100 :
b10 <
0'
#211
1'
#212
b100 O
b1111111111111111111111111111111111111111111111111001110001110100 :
b11 <
0'
#213
1'
#214
b101 O
b11111111111111111111111111111111111111111111111111111111111111111001110001110100 :
b100 <
0'
#215
1'
#216
b110 O
b111111111111111111111111111111111111111111111111111111111111111111111111111111111001110001110100 :
b101 <
0'
#217
1'
#218
b0 $
b0 -
b0 J
b0 L
b111 O
b1111111111111111111111111111111111111111111111111111111111111111111111111111111111111111111111111001110001110100 :
b110 <
0'
#219
1'
#220
bz #
bz ,
bz I
bz K
b1000 O
b111 <
0'
#221
1'
#222
b111 !
b111 )
b111 ?
b111 /
b1110100 "
b1110100 *
b1110100 @
b1110100 0
06
b0 #
b0 ,
b0 I
b0 8
b1000 <
0'
#223
bz $
bz -
bz J
bz L
1'
#224
bz 5
bz 0
bz /
b1110 &
b1110 .
b1110 >
b1110 A
b11110000 "
b11110000 *
b11110000 @
b11110000 D
b101 !
b101 )
b101 ?
b101 C
b11110000 E
b1110100 F
b1110100 G
0'
#225
bx0000000011110000 1
b101 5
1'
#226
b1x1 !
b1x1 )
b1x1 ?
b111 /
b0 &
b0 .
b0 >
b0 A
0'
#227
1'
#228
bz 5
bz /
b1110 &
b1110 .
b1110 >
b1110 A
bz "
bz *
bz @
bz D
b1 !
b1 )
b1 ?
b1 C
0'
#229
b1 5
1'
#230
bx1 !
bx1 )
bx1 ?
b111 /
b11110000 "
b11110000 *
b11110000 @
b11110000 0
b0 &
b0 .
b0 >
b0 A
0'
#231
1'
#232
bz 5
bz "
bz *
bz @
bz 0
bz /
b1110 &
b1110 .
b1110 >
b1110 A
b11110000 F
b11110000 G
b10 !
b10 )
b10 ?
b10 C
0'
#233
b10 5
1'
#234
bx1x !
bx1x )
bx1x ?
b111 /
b1001110011110000 "
b1001110011110000 *
b1001110011110000 @
b1001110011110000 0
b0 &
b0 .
b0 >
b0 A
0'
#235
1'
#236
bz 5
bz 0
bz /
b1110 &
b1110 .
b1110 >
b1110 A
b1111111100000000 "
b1111111100000000 *
b1111111100000000 @
b1111111100000000 D
b1111111100000000 E
b1001110011110000 F
b1001110011110000 G
b110 !
b110 )
b110 ?
b110 C
0'
#237
bx1111111100000000 1
b110 5
1'
#238
b11x !
b11x )
b11x ?
b111 /
b0 &
b0 .
b0 >
b0 A
0'
#239
1'
#240
bz 5
bz /
b1110 &
b1110 .
b1110 >
b1110 A
bz "
bz *
bz @
bz D
b10 !
b10 )
b10 ?
b10 C
0'
#241
b10 5
1'
#242
bx1x !
bx1x )
bx1x ?
b111 /
b1111111100000000 "
b1111111100000000 *
b1111111100000000 @
b1111111100000000 0
b0 &
b0 .
b0 >
b0 A
0'
#243
1'
#244
bz 5
bz "
bz *
bz @
bz 0
bz /
b1110 &
b1110 .
b1110 >
b1110 A
b1111111100000000 F
b1111111100000000 G
b11 !
b11 )
b11 ?
b11 C
0'
#245
b11 5
1'
#246
bx11 !
bx11 )
bx11 ?
b111 /
b1111111100000000 "
b1111111100000000 *
b1111111100000000 @
b1111111100000000 0
b0 &
b0 .
b0 >
b0 A
0'
#247
1'
#248
b1110 &
b1110 .
b1110 >
b1110 A
b111 !
b111 )
b111 ?
bz C
0'
#249
1'
#250
b1111111111111111 "
b1111111111111111 *
b1111111111111111 @
b1111111111111111 0
b10 2
b0 &
b0 .
b0 >
b0 A
0'
#251
1'
#252
bz 5
bz 0
bz /
b1110 &
b1110 .
b1110 >
b1110 A
b101010101010101 "
b101010101010101 *
b101010101010101 @
b101010101010101 D
b111 C
b1010101010101010101010101010101 E
b11111111111111111111111100000000 F
b1111111111111111 G
0'
#253
bx0101010101010101 1
b111 5
1'
#254
b111 /
b1010101010101010101010101010101 1
b0 2
b0 &
b0 .
b0 >
b0 A
0'
#255
1'
#256
bz 5
bz /
b1110 &
b1110 .
b1110 >
b1110 A
b11 !
b11 )
b11 ?
bz "
bz *
bz @
bz D
b11 C
0'
#257
b11 5
1'
#258
bx11 !
bx11 )
bx11 ?
b111 /
b101010101010101 "
b101010101010101 *
b101010101010101 @
b101010101010101 0
b0 &
b0 .
b0 >
b0 A
0'
#259
1'
#260
b1110 &
b1110 .
b1110 >
b1110 A
b11111111111111110101010101010101 F
b101010101010101 G
b111 !
b111 )
b111 ?
bz C
0'
#261
1'
#262
b10 2
b0 &
b0 .
b0 >
b0 A
0'
#263
1'
#264
bz 5
bz "
bz *
bz @
bz 0
bz /
b10001 &
b10001 .
b10001 >
b10001 A
b11 !
b11 )
b11 ?
b11 C
b100010000 B
b1010101010101010101010101010101 F
0'
#265
b10001 3
b10001 %
b10001 +
b10001 H
b10001 7
b11 5
1'
#266
b10 #
b10 ,
b10 I
b10 8
b0 2
b0 &
b0 .
b0 >
b0 A
0'
#267
1'
#268
bz #
bz ,
bz I
bz 8
bz !
bz )
bz ?
bz C
0'
