2-Lab/mem.sv
module mem #(
    parameter MEM_ADDR_SIZE = 10 + 9, 
    parameter CACHE_OFFSET_SIZE = 4,
    parameter BUS_SIZE = 16,
    parameter CACHE_LINE_SIZE = 16
    ) (
    input clk,
    input reset,
    input [MEM_ADDR_SIZE-CACHE_OFFSET_SIZE-1:0] address,
    inout [BUS_SIZE-1:0] data,
    input [2-1:0] command
    );
    parameter MEM_SIZE = 1 << (MEM_ADDR_SIZE-CACHE_OFFSET_SIZE);   // 512KB = 2^9 * 2^10 = 2^19

    localparam  C2_NOP      = 3'd0,
                C2_RESPONSE = 3'd1,
                C2_READ     = 3'd2,
                C2_WRITE    = 3'd3;

    reg [CACHE_LINE_SIZE*8-1:0] storage [MEM_SIZE-1:0]; // 2^15 16-byte lines
    reg [BUS_SIZE-1:0] data_buff; // single bus
    reg [2-1:0] command_buff;

    reg [CACHE_OFFSET_SIZE-1:0] rwPosition; // ptr to next 2 bytes to read/write

    integer SEED = 225526;

    always @(posedge clk or posedge reset) begin
        if (reset) begin
            for (int i = 0; i < 16; i=i+1) begin
                storage[i] = $random(SEED)>>16;
                $display("%d %b", i, storage[i]);
            end
            $display("filled");

            data_buff = 0;
            command_buff = 0;
            rwPosition = 0;
        end else begin
            command_buff = 0;
            if (command == C2_READ) begin
                // READ
                for (int i=0; i<CACHE_LINE_SIZE; i=i+1) begin
                    data_buff[i] = storage[address][rwPosition*8 + i];
                end
                rwPosition += 2;
            end else if (command == C2_WRITE) begin
                // WRITE
                for (int i=0; i<CACHE_LINE_SIZE; i=i+1) begin
                    storage[address + (i << CACHE_OFFSET_SIZE)] = data[i];
                end
                command_buff = 1;
            end else begin
                rwPosition = 0;
            end
        end
    end
    // assign command = command_buff;
    assign data = data_buff;
endmodule

2-Lab/cache.sv
module cache#(
    parameter BUS_SIZE = 16,
    parameter MEM_ADDR_SIZE = 10 + 9,   // log2(MEM_SIZE)
    parameter CACHE_OFFSET_SIZE = 4,    // log2(CACHE_LINE_SIZE)
    parameter CACHE_LINE_SIZE   = 16
    ) (
    input clk,
    input reset,
    // inout [MEM_ADDR_SIZE-1:0] cpu_address,
    // inout [BUS_SIZE-1:0] cpu_data,
    // inout [3-1:0] cpu_command,

    inout [MEM_ADDR_SIZE-CACHE_OFFSET_SIZE-1:0] mem_address,
    inout [BUS_SIZE-1:0] mem_data,
    inout [2-1:0] mem_command
    );

    parameter CACHE_WAY         = 2;

    parameter CACHE_LINE_COUNT  = 64;
    parameter CACHE_SIZE        = CACHE_LINE_COUNT * CACHE_LINE_SIZE;
   
    parameter CACHE_SET_SIZE    = 5;    // log2(CACHE_LINE_COUNT/CACHE_WAY)
    parameter CACHE_TAG_SIZE    = 10;   // CACHE_LINE_SIZE - CACHE_SET_SIZE - CACHE_OFFSET_SIZE

    localparam  C1_NOP      = 3'd0;
    localparam  C1_READ8    = 3'd1;
    localparam  C1_READ16   = 3'd2,
                C1_READ32   = 3'd3,
                C1_INV_LINE = 3'd4,
                C1_WRITE8   = 3'd5,
                C1_WRITE16  = 3'd6,
                C1_WRITE32  = 3'd7;

    localparam  C2_NOP      = 2'd0,
                C2_RESPONSE = 2'd1,
                C2_READ     = 2'd2,
                C2_WRITE    = 2'd3;

    // localparam  IDLE        = 3'd0,
    //             READ        = 3'd1,
    //             WRITE       = 3'd2,
    //             READMM      = 3'd3,
    //             WAITFORMM   = 3'd4,
    //             UPDATEMM    = 3'd5,
    //             UPDATECACHE = 3'd6;

    // reg [3-1:0] state;

    // STORAGE
    // reg valid_array [CACHE_SET_SIZE-1:0][CACHE_WAY-1:0];
    // reg dirty_array [CACHE_SET_SIZE-1:0][CACHE_WAY-1:0];
    // reg last_used_array [CACHE_SET_SIZE-1:0][CACHE_WAY-1:0]; // lRU
    // reg [CACHE_TAG_SIZE-1:0] tag_array [CACHE_SET_SIZE-1:0][CACHE_WAY-1:0];
    // reg [CACHE_LINE_SIZE*8-1:0] data_array [CACHE_SET_SIZE-1:0][CACHE_WAY-1:0]; // stores lines

    reg [MEM_ADDR_SIZE-1:0] cpu_address_buff;
    reg [CACHE_OFFSET_SIZE-1:0] cpu_offset_buff;
    // reg [CACHE_LINE_SIZE*8-1:0] cpu_data_buff; // single line
    // reg [3-1:0] cpu_command_buff;
    
    reg [MEM_ADDR_SIZE-CACHE_OFFSET_SIZE-1:0] mem_address_buff;
    reg [CACHE_LINE_SIZE*8-1:0] mem_line_buff; // single line
    reg [BUS_SIZE-1:0] mem_data_buff;
    reg [2-1:0] mem_command_buff;
    
    // integer bitOfOp;
    

    task delay;
        begin
            @(negedge clk);
        end
    endtask	

    initial begin
        $dumpfile("dump_cache.vcd"); 
        $dumpvars;
        
        // init
        mem_line_buff = 0;
        mem_command_buff = C2_NOP;
        mem_address_buff = 15'b000000000000000;
        delay;
        delay;
        delay;

        // set
        cpu_address_buff = 19'b0000000000001010001;
        cpu_offset_buff = cpu_address_buff[3:0];
        mem_address_buff = cpu_address_buff >> CACHE_OFFSET_SIZE;
        mem_command_buff = C2_READ;
        delay;

        // read
        for (int i=0; i<CACHE_LINE_SIZE/2; i=i+1) begin
            mem_line_buff[BUS_SIZE*i +: BUS_SIZE] = mem_data;
            delay;
        end

        $display ("mem_line_buff = %b",mem_line_buff);
        $display ("8 bit = %b", mem_line_buff[cpu_offset_buff*8 +: 8]);
        $finish();
    end
    assign mem_command = mem_command_buff;
    assign mem_address = mem_address_buff;

    // always @(posedge clk) begin
    //     case(state)
    //         IDLE: begin
    //             case (cpu_command)
    //                 C1_NOP: begin
                        
    //                 end
    //                 C1_READ8: begin
    //                     state = READ;
    //                     mem_address_buff = cpu_address;
    //                     bitOfOp = 8;
    //                 end
    //                 C1_READ16: begin
                        
    //                     bitOfOp = 16;
    //                 end
    //                 C1_READ32: begin
                        
    //                     bitOfOp = 32;
    //                 end
    //                 C1_INV_LINE: begin
                        
    //                 end
    //                 C1_WRITE8: begin
                        
    //                     bitOfOp = 8;
    //                 end
    //                 C1_WRITE16: begin
                        
    //                     bitOfOp = 16;
    //                 end
    //                 C1_WRITE32: begin
                        
    //                     bitOfOp = 32;
    //                 end
    //             endcase
    //         end
    //         READ: begin
    //             reg [CACHE_SET_SIZE-1:0] set = cpu_address >> CACHE_OFFSET_SIZE;
    //             reg [CACHE_TAG_SIZE-1:0] tag = cpu_address >> (CACHE_SET_SIZE + CACHE_OFFSET_SIZE);

    //             if (valid_array[set][0] == 1 && tag_array[set][0] == tag) begin

    //             end else if (valid_array[set][1] == 1 && tag_array[set][1] == tag) begin
                    
    //             end else begin
    //                 // miss
    //                 if (dirty_array[set][last_used_array[set]] == 1) begin
    //                     // UPDATEMM
    //                     // dirty
    //                     // flag
    //                 end else begin
    //                     // READMM
    //                 end
    //             end

    //             assign hit_w0 = vw0 & (tagdata == rtag0[10:0]);
    //             assign hit_w1 = vw1 & (tagdata == rtag1[10:0]);
    //             assign hit = hit_w0 | hit_w1;
    //         end
    //         WRITE: begin
                
    //         end
    //         READMM: begin
                
    //         end
    //         WAITFORMM: begin
                
    //         end
    //         UPDATEMM: begin
                
    //         end
    //         UPDATECACHE: begin
                
    //         end
    //     endcase
    // end

    // assign mem_address = mem_address_buff;

    // // CPU
    // always @(posedge clk) begin
    //     mem_command_buff = 0;
    //     // C1_READ8
    //     if (cpu_command == 3) begin
    //         reg [CACHE_SET_SIZE-1:0] set = cpu_address >> CACHE_OFFSET_SIZE;
    //         reg [CACHE_TAG_SIZE-1:0] tag = cpu_address >> (CACHE_SET_SIZE + CACHE_OFFSET_SIZE);
    //         reg found = 0;
    //         for (int i=0; i<CACHE_SET_SIZE; i=i+1) begin
    //             if (tag_array[set][i] == tag) begin
    //                 // Retrurn data
    //                 cpu_data_buff = data_array[set][i];
    //                 cpu_command_buff = 7;
    //             end
    //         end

    //         if (found == 0) begin 
    //             // Request from mem
    //             // Set valid 
    //             valid_array[set][i] = 1;
    //         end

    //     end
    // end
    // assign mem_command = mem_command_buff;
    // assign mem_data = mem_line_buff;

    // // MEM
    // always @(posedge clk) begin
    //     cpu_command_buff = 0;
    //     // C2_READ
    //     if (mem_command == 1) begin
    //         reg [CACHE_SET_SIZE-1:0] set = mem_address >> CACHE_OFFSET_SIZE;
    //         reg [CACHE_TAG_SIZE-1:0] tag = mem_address >> (CACHE_SET_SIZE + CACHE_OFFSET_SIZE);
    //         reg found = 0;
    //         for (int i=0; i<CACHE_SET_SIZE; i=i+1) begin
    //             if (valid_array[set][i] == 0) begin
    //                 found = 1;
    //                 valid_array[set][i] = 1;
    //                 dirty_array[set][i] = 0;
    //                 tag_array[set][i] = tag;
    //                 data_array[set][i] = mem_data;
    //             end
    //         end
    //         if (found == 0) begin
    //             // search for not dirty
    //             // if all dirty write one and replace with new data
    //         end
    //         cpu_data_buff = mem_data;

    //         cpu_command_buff = 7;
    //     end
    // end
    // assign cpu_command = cpu_command_buff;
    // assign cpu_data = cpu_data_buff;

    

endmodule

2-Lab/testbench.sv
module testbench ();
    parameter BUS_SIZE = 16;
    parameter MEM_ADDR_SIZE = 10 + 9;   // log2(MEM_SIZE)
    parameter CACHE_OFFSET_SIZE = 4;    // log2(CACHE_LINE_SIZE)
    parameter CACHE_LINE_SIZE = 16;
    // wire [MEM_ADDR_SIZE-1:0] cpu_address;
    // wire [BUS_SIZE-1:0] cpu_data;
    // wire [3-1:0] cpu_command;
    wire [MEM_ADDR_SIZE-CACHE_OFFSET_SIZE-1:0] mem_address;
    wire [BUS_SIZE-1:0] mem_data;
    wire [2-1:0] mem_command;

    // cpu cpu(
    //     .clk(clk),
    //     .address(cpu_address),
    //     .data(cpu_data),
    //     .command(cpu_command)
    // );
    // cache cache(
    //     .clk(clk)
        
    //     .cpu_address(cpu_address),
    //     .cpu_data(cpu_data),
    //     .cpu_command(cpu_command)
    //     .mem_address(mem_address),
    //     .mem_data(mem_data),
    //     .mem_command(mem_command)
    // );
    reg clk;
    reg reset;


    cache #(BUS_SIZE, MEM_ADDR_SIZE, CACHE_OFFSET_SIZE, CACHE_LINE_SIZE) 
    cache1 (clk, reset, mem_address, mem_data, mem_command);

    mem #(MEM_ADDR_SIZE, CACHE_OFFSET_SIZE, BUS_SIZE, CACHE_LINE_SIZE) 
    m1(clk, reset, mem_address, mem_data, mem_command);

    initial begin
        reset = 0;
        #1 reset = 1;
        #1 reset = 0;

        clk = 1'd0;
        forever begin
            #1 clk = ~clk;
            $display("addr: %b", mem_address);
            $display("data: %b", mem_data);
            $display("command: %b", mem_command);
        end
    end

endmodule

2-Lab/dump_cache.vcd
$date
	Tue Nov 29 22:41:30 2022
$end
$version
	Icarus Verilog
$end
$timescale
	1s
$end
$scope module testbench $end
$var wire 16 ! mem_data [15:0] $end
$var wire 2 " mem_command [1:0] $end
$var wire 15 # mem_address [14:0] $end
$var reg 1 $ clk $end
$var reg 1 % reset $end
$scope module cache1 $end
$var wire 1 $ clk $end
$var wire 15 & mem_address [14:0] $end
$var wire 2 ' mem_command [1:0] $end
$var wire 1 % reset $end
$var wire 16 ( mem_data [15:0] $end
$var reg 19 ) cpu_address_buff [18:0] $end
$var reg 4 * cpu_offset_buff [3:0] $end
$var reg 15 + mem_address_buff [14:0] $end
$var reg 2 , mem_command_buff [1:0] $end
$var reg 128 - mem_line_buff [127:0] $end
$scope begin $ivl_for_loop0 $end
$var integer 32 . i [31:0] $end
$upscope $end
$scope task delay $end
$upscope $end
$upscope $end
$scope module m1 $end
$var wire 15 / address [14:0] $end
$var wire 1 $ clk $end
$var wire 2 0 command [1:0] $end
$var wire 16 1 data [15:0] $end
$var wire 1 % reset $end
$var reg 2 2 command_buff [1:0] $end
$var reg 16 3 data_buff [15:0] $end
$var reg 4 4 rwPosition [3:0] $end
$var integer 32 5 SEED [31:0] $end
$scope begin $ivl_for_loop1 $end
$var integer 32 6 i [31:0] $end
$upscope $end
$scope begin $ivl_for_loop2 $end
$var integer 32 7 i [31:0] $end
$upscope $end
$scope begin $ivl_for_loop3 $end
$var integer 32 8 i [31:0] $end
$upscope $end
$upscope $end
$upscope $end
$enddefinitions $end
#0
$dumpvars
b0 8
b0 7
b0 6
b110111000011110110 5
bx 4
bx 3
bx 2
bx 1
b0 0
b0 /
b0 .
b0 -
b0 ,
b0 +
bx *
bx )
bx (
b0 '
b0 &
0%
x$
b0 #
b0 "
bx !
$end
#1
b0 4
b0 2
b0 !
b0 (
b0 1
b0 3
b10000 6
b1001110111001100111111000100110 5
1%
#2
0$
0%
#3
1$
#4
0$
#5
1$
#6
b10 "
b10 '
b10 0
b10 ,
b101 #
b101 &
b101 /
b101 +
b1 *
b1010001 )
0$
#7
b10 4
b111001100110 !
b111001100110 (
b111001100110 1
b111001100110 3
b10000 7
1$
#8
b111001100110 -
0$
#9
b100 4
b0 !
b0 (
b0 1
b0 3
b10000 7
1$
#10
b1 .
0$
#11
b110 4
b10000 7
1$
#12
b10 .
0$
#13
b1000 4
b10000 7
1$
#14
b11 .
0$
#15
b1010 4
b10000 7
1$
#16
b100 .
0$
#17
b1100 4
b10000 7
1$
#18
b101 .
0$
#19
b1110 4
b10000 7
1$
#20
b110 .
0$
#21
b0 4
b10000 7
1$
#22
b111 .
0$
#23
b10 4
b111001100110 !
b111001100110 (
b111001100110 1
b111001100110 3
b10000 7
1$
#24
b1000 .
0$
